Workbook

Sheet 入力
A1: 【入力フォーム】ここだけ入力 | C1: =IF(マスタ!I8="","(カレンダーURLはマスタシートI8へ)",HYPERLINK(マスタ!I8,"→ 共有カレンダーを開く")) -> (カレンダーURLはマスタシートI8へ)
A2: =IF(COUNTBLANK(B14)+COUNTBLANK(B15)+COUNTBLANK(B18)+COUNTBLANK(B21)+COUNTBLANK(B50)+COUNTBLANK(B61)+COUNTBLANK(B82)=0,"✓ 必須項目はすべて入力済みです","未入力の必須項目(*): "&(COUNTBLANK(B14)+COUNTBLANK(B15)+COUNTBLANK(B18)+COUNTBLANK(B21)+COUNTBLANK(B50)+COUNTBLANK(B61)+COUNTBLANK(B82))&" 件") -> 未入力の必須項目(*): 7 件
A3: 黄色=入力欄(空欄で配布・記入例は右のグレー文字) / ▼=リスト選択 / 緑=自動 / *=必須
A4: ■ 1. お相手(誰が)
A5: 会社名 | C5: 例: 田中産業株式会社
A6: 団体名 | C6: 例: 田中産業 親睦会ご一行様
A7: ツアー名 | C7: 例: 2026年度 社員親睦旅行
A8: 概要 | C8: 例: 社員旅行(宴会・送迎あり)
A9: 取引先/エージェント | C9: 例: 直受け / ㈱○○トラベル
A10: 先方担当者・連絡先 | C10: 例: 田中 一郎 様(090-0000-0000)
A11: 国籍 / Tour No. | C11: 例: Japan / -
A12: 添乗員・TEL | C12: 例: 山田様(080-0000-0000)
A13: ■ 2. 日程(いつ)
A14: 利用開始日(C/I) * | C14: 例: 2026/8/15
A15: 利用終了日(C/O) * | C15: 例: 2026/8/16
A16: 到着手段・時刻 | C16: 例: 貸切バス 15:00着予定
A17: 出発時刻 | C17: 例: 10:00発
A18: お出迎え・挨拶 ▼ * | C18: 例: なし/セールス立ち会い/支配人挨拶 ←必ず選択
A19: 挨拶詳細(誰が・どこで) | C19: 例: セールス清水 15:00 ロビーでお出迎え・挨拶
A20: ■ 3. 人数(大人・子供・添乗員は別々に入力)
A21: 大人 * | C21: 例: 38
A22: 子供(4-12歳) | C22: 例: 2
A23: 添乗員・乗務員 | C23: 例: 1
A24: 人数(合計) | B24: =IF(COUNT(B21,B22,B23)=0,"",N(B21)+N(B22)+N(B23)) | C24: 自動合計(触らない)
A25: ■ 4. 宿泊
A26: 宿泊有無 ▼ | C26: 例: ▼から選択
A27: チェックイン時刻 | C27: 例: 15:00
A28: チェックアウト時刻 | C28: 例: 10:00
A29: 部屋タイプ ▼ | B29: 室数 | C29: 料金(1室1泊) | D29: 泊数 | E29: 金額
A30: 例: Superior Twin | B30: 15 | C30: 14,960 | D30: (自動) | E30: (自動)
D31: =IF(OR(A31="",B14="",B15=""),"",B15-B14) | E31: =IF(OR(A31="",COUNT(B31,C31,D31)<3),"",B31*C31*D31)
D32: =IF(OR(A32="",B14="",B15=""),"",B15-B14) | E32: =IF(OR(A32="",COUNT(B32,C32,D32)<3),"",B32*C32*D32)
D33: =IF(OR(A33="",B14="",B15=""),"",B15-B14) | E33: =IF(OR(A33="",COUNT(B33,C33,D33)<3),"",B33*C33*D33)
D34: =IF(OR(A34="",B14="",B15=""),"",B15-B14) | E34: =IF(OR(A34="",COUNT(B34,C34,D34)<3),"",B34*C34*D34)
D35: =IF(OR(A35="",B14="",B15=""),"",B15-B14) | E35: =IF(OR(A35="",COUNT(B35,C35,D35)<3),"",B35*C35*D35)
D36: =IF(OR(A36="",B14="",B15=""),"",B15-B14) | E36: =IF(OR(A36="",COUNT(B36,C36,D36)<3),"",B36*C36*D36)
D37: =IF(OR(A37="",B14="",B15=""),"",B15-B14) | E37: =IF(OR(A37="",COUNT(B37,C37,D37)<3),"",B37*C37*D37)
D38: =IF(OR(A38="",B14="",B15=""),"",B15-B14) | E38: =IF(OR(A38="",COUNT(B38,C38,D38)<3),"",B38*C38*D38)
A39: 宿泊小計 | B39: =SUM(E31:E38) -> 0 | C39: 自動計算 → 見積書に部屋タイプごと自動で載ります
A40: 宿泊特記 | C40: 例: 1階希望3名(車椅子貸出1名)
A41: ■ 5. 食事(1〜3日目×朝食・夕食。会場▼=4店舗 / 時刻▼=15分毎)
A42: 区分(自動) | B42: 内容 | C42: 会場 ▼ | D42: 時刻 ▼ | E42: 数量
B43: 例: 宴会コース+飲放90分 | C43: ザ・プレート | D43: 18:00 | E43: 40
A44: ="1日目"&IF(B14="","","("&TEXT(B14+0,"m/d")&")")&" 朝食" -> 1日目 朝食
A45: ="1日目"&IF(B14="","","("&TEXT(B14+0,"m/d")&")")&" 夕食" -> 1日目 夕食
A46: ="2日目"&IF(B14="","","("&TEXT(B14+1,"m/d")&")")&" 朝食" -> 2日目 朝食
A47: ="2日目"&IF(B14="","","("&TEXT(B14+1,"m/d")&")")&" 夕食" -> 2日目 夕食
A48: ="3日目"&IF(B14="","","("&TEXT(B14+2,"m/d")&")")&" 朝食" -> 3日目 朝食
A49: ="3日目"&IF(B14="","","("&TEXT(B14+2,"m/d")&")")&" 夕食" -> 3日目 夕食
A50: アレルギー * | C50: 例: なし ←無い場合も必ず記入 / 甲殻類3名(名簿は料飲へ)
A51: ■ 6. 宴会・会場
A52: 会場 ▼ | C52: 例: ▼から選択
A53: 設営/本番/撤収 | C53: 例: 17:00設営 / 18:00-20:00 / 21:00撤収
A54: レイアウト ▼ | C54: 例: ▼から選択
A55: 機材・備品 | C55: 例: マイク2・プロジェクター
A56: 進行メモ | C56: 例: 19:00頃 社長表彰(照明・マイク)
A57: ■ 7. 送迎
A58: 往路 | C58: 例: 8/15 上越妙高駅 14:30発 → ホテル(バス2台)
A59: 復路 | C59: 例: 8/16 ホテル 10:00発 → 上越妙高駅
A60: ■ 8. 条件・ステータス
A61: ステータス ▼ * | C61: 例: ▼から選択
A62: 確度 ▼ | C62: 例: S/A/B/C から選択
A63: 仮予約期限 | C63: 例: 2026/7/31 ←仮予約なら必須(空欄だと赤)
A64: 支払方法 ▼ | C64: 例: ▼から選択
A65: 税・サービス料 ▼ | C65: 例: サ込税別 など
A66: ■ 9. 見積明細(宴会・料飲・送迎など。宿泊は上の部屋タイプ表から自動)
A67: 項目 ▼ | B67: 内容 | C67: 単価 | D67: 数量 | E67: 単位 ▼
A68: 例: 宿泊 | B68: 1泊2食付(Superior Twin) | C68: 15,000 | D68: 40 | E68: 名
A79: 入湯税(円) | C79: 例: 150円×宿泊人数×泊数 = 6,000
A80: 値引き(マイナス) | C80: 例: -10,000
A81: ■ 10. 社内管理
A82: 予約番号 * | C82: 例: 2026-070
A83: 担当営業 | C83: 例: 清水
A84: 担当(手配/現地) | C84: 例: 手配:宮本 / 現地:小池
A85: コード略号(英字4) | C85: 例: TANA ←団体名ローマ字先頭4字
A86: ブロックコード | B86: =IF(OR(B14="",B85=""),"",TEXT(B14,"mmdd")&UPPER(B85)&"01") | C86: 自動生成(Opera用)。手修正可
A87: 見積番号 | C87: 例: Q-2026-0001
A88: 発行日 | C88: 例: 2026/7/17
A89: 見積有効期限 | C89: 例: 2026/8/1
A90: ■ 11. 特記事項・引き継ぎメモ(共有シートに載ります)
A100: ▼カレンダー転記用(この行をコピーして共有カレンダーの案件一覧に貼り付け→値貼り付け)
A101: =IF(B82="","",B82) | B101: =IF(B86="","",B86) | C101: =IF(B61="","",B61) | D101: =IF(B62="","",B62) | E101: =IF(B14="","",B14) | F101: =IF(B15="","",B15) | H101: =IF(B63="","",B63) | J101: =IF(B6="","",B6) | K101: =IF(B8="","",B8) | L101: =IF(B9="","",B9) | M101: =IF(B24="","",B24) | N101: =IF(B52="","",B52) | O101: =IF(B83="","",B83)

Sheet 社内共有シート
A1: 団体案件 社内共有シート | E1: ブロックコード | F1: =IF(入力!B86="","",入力!B86)
E2: 予約番号 | F2: =IF(入力!B82="","",入力!B82)
A3: ステータス | B3: =IF(入力!B61="","",入力!B61) | E3: 営業担当 | F3: =IF(入力!B83="","",入力!B83)
A4: ■ 基本情報
A5: 会社名 | B5: =IF(入力!B5="","",入力!B5) | E5: 利用期間 | F5: =IF(入力!B14="","",TEXT(入力!B14,"m/d")&" 〜 "&IF(入力!B15="","",TEXT(入力!B15,"m/d")))
A6: 団体名 | B6: =IF(入力!B6="","",入力!B6) | E6: 人数 | F6: =IF(入力!B24="","",入力!B24&"名(大人"&N(入力!B21)&"・子供"&N(入力!B22)&"・添乗員"&N(入力!B23)&")")
A7: ツアー名 | B7: =IF(入力!B7="","",入力!B7) | E7: 到着 | F7: =IF(入力!B16="","",入力!B16)
A8: 概要 | B8: =IF(入力!B8="","",入力!B8) | E8: 出発 | F8: =IF(入力!B17="","",入力!B17)
A9: 先方担当 | B9: =IF(入力!B10="","",入力!B10) | E9: 支払方法 | F9: =IF(入力!B64="","",入力!B64)
A10: 添乗員 | B10: =IF(入力!B12="","",入力!B12) | E10: 取引先 | F10: =IF(入力!B9="","",入力!B9)
A11: 確度/期限 | B11: =IF(入力!B62="","",入力!B62)&IF(入力!B63="",""," / 仮予約期限: "&TEXT(入力!B63,"m/d")) | E11: 手配/現地 | F11: =IF(入力!B84="","",入力!B84)
A12: ■ 宿泊
A13: 部屋構成 | B13: =_xlfn.TEXTJOIN("、",TRUE(),IF(入力!A31="","",入力!A31&"×"&入力!B31&"室"),IF(入力!A32="","",入力!A32&"×"&入力!B32&"室"),IF(入力!A33="","",入力!A33&"×"&入力!B33&"室"),IF(入力!A34="","",入力!A34&"×"&入力!B34&"室"),IF(入力!A35="","",入力!A35&"×"&入力!B35&"室"),IF(入力!A36="","",入力!A36&"×"&入力!B36&"室"),IF(入力!A37="","",入力!A37&"×"&入力!B37&"室"),IF(入力!A38="","",入力!A38&"×"&入力!B38&"室")) | E13: C/I・C/O | F13: =IF(入力!B27="","",入力!B27)&IF(入力!B28="",""," / "&入力!B28)
A14: 宿泊特記 | B14: =IF(入力!B40="","",入力!B40)
A15: ■ 食事(入力のあるものだけ表示)
A16: 食事 | B16: =_xlfn.TEXTJOIN(CHAR(10),TRUE(),IF(AND(入力!B44="",入力!C44="",入力!D44=""),"",入力!A44&" "&入力!D44&" "&入力!C44&" "&入力!B44&IF(入力!E44="",""," "&入力!E44&"名")),IF(AND(入力!B45="",入力!C45="",入力!D45=""),"",入力!A45&" "&入力!D45&" "&入力!C45&" "&入力!B45&IF(入力!E45="",""," "&入力!E45&"名")),IF(AND(入力!B46="",入力!C46="",入力!D46=""),"",入力!A46&" "&入力!D46&" "&入力!C46&" "&入力!B46&IF(入力!E46="",""," "&入力!E46&"名")),IF(AND(入力!B47="",入力!C47="",入力!D47=""),"",入力!A47&" "&入力!D47&" "&入力!C47&" "&入力!B47&IF(入力!E47="",""," "&入力!E47&"名")),IF(AND(入力!B48="",入力!C48="",入力!D48=""),"",入力!A48&" "&入力!D48&" "&入力!C48&" "&入力!B48&IF(入力!E48="",""," "&入力!E48&"名")),IF(AND(入力!B49="",入力!C49="",入力!D49=""),"",入力!A49&" "&入力!D49&" "&入力!C49&" "&入力!B49&IF(入力!E49="",""," "&入力!E49&"名")))
A22: アレルギー | B22: =IF(入力!B50="","",入力!B50)
A23: ■ 宴会・会場
A24: 会場 | B24: =IF(入力!B52="","",入力!B52) | E24: 設営/撤収 | F24: =IF(入力!B53="","",入力!B53)
A25: レイアウト | B25: =IF(入力!B54="","",入力!B54) | E25: 機材 | F25: =IF(入力!B55="","",入力!B55)
A26: 進行メモ | B26: =IF(入力!B56="","",入力!B56)
A27: ■ 送迎
A28: 往路 | B28: =IF(入力!B58="","",入力!B58) | E28: 復路 | F28: =IF(入力!B59="","",入力!B59)
A29: ■ 料金・請求
A30: 見積合計 | B30: =IF(見積書!G39=0,"","¥"&TEXT(見積書!G39,"#,##0")&"(税込)") | E30: 請求状況
A31: ■ フロント引き継ぎ・チェック欄(済んだら□にチェック・サイン)
A32: お出迎え・挨拶 | B32: =IF(入力!B18="","※未入力!! 入力シートで必ず選択してください",入力!B18&IF(入力!B19="",""," — "&入力!B19)) -> ※未入力!! 入力シートで必ず選択してください
A33: 引き継ぎ | B33: 営業サイン: | E33: フロント受領サイン:
A34: 2日前 | B34: =IF(入力!B14="","","〆"&TEXT(入力!B14+(-2),"m/d")&" ")&"□館内案内作成 □名前シール作成 □部屋割り連絡" -> □館内案内作成 □名前シール作成 □部屋割り連絡 | G34: 担当:
A35: 1日前 | B35: =IF(入力!B14="","","〆"&TEXT(入力!B14+(-1),"m/d")&" ")&"□料金確認 □館内案内印刷 □紙の版数照合" -> □料金確認 □館内案内印刷 □紙の版数照合 | G35: 担当:
A36: 当日 | B36: =IF(入力!B14="","","〆"&TEXT(入力!B14+(0),"m/d")&" ")&"□名前シール印刷 □添乗員到着時間確認 □お出迎え・挨拶手配" -> □名前シール印刷 □添乗員到着時間確認 □お出迎え・挨拶手配 | G36: 担当:
A37: ■ 特記事項・引き継ぎメモ
A38: =IF(入力!A91="","",入力!A91)

Sheet 見積書
B1: 御 見 積 書 | F1: 見積番号 | G1: =IF(入力!B87="","",入力!B87)
F2: 発行日 | G2: =IF(入力!B88="","",入力!B88)
F3: ブロックコード | G3: =IF(入力!B86="","",入力!B86)
A4: =IF(入力!B5="","",入力!B5&" 御中") | F4: 【ロゴ】
A5: =IF(入力!B6="","",入力!B6)
A6: =IF(入力!B7="","",入力!B7) | F6: =マスタ!I2 -> (ホテル名を入力)
A7: =IF(入力!B10="","","ご担当: "&入力!B10) | F7: =マスタ!I3 -> (住所・TELを入力)
A8: 下記のとおりお見積り申し上げます。 | F8: ="インボイス登録番号 "&マスタ!I4 -> インボイス登録番号 T0000000000000
F9: 担当: | G9: =マスタ!I5 -> 0
A10: 件名 | C10: =IF(入力!B7<>"",入力!B7,IF(入力!B6<>"",入力!B6,IF(入力!B5="","",入力!B5&"様"))) | F10: 御見積合計(税込)
A11: ご利用期間 | C11: =IF(入力!B14="","",TEXT(入力!B14,"yyyy/m/d")&" 〜 "&IF(入力!B15="","",TEXT(入力!B15,"m/d"))) | F11: =G31
A12: ご利用人数 | C12: =IF(入力!B24="","",入力!B24&"名(大人"&N(入力!B21)&"・子供"&N(入力!B22)&"・添乗員"&N(入力!B23)&")")
A13: お支払方法 | C13: =IF(入力!B64="","",入力!B64) | F13: 見積有効期限
F14: =IF(入力!B89="","",入力!B89)
A15: No. | B15: 項目 | C15: 内容 | D15: 単価 | E15: 数量 | F15: 単位 | G15: 金額
A16: =IF(入力!A31="","",ROW()-15) | B16: =IF(入力!A31="","","宿泊") | C16: =IF(入力!A31="","",入力!A31&IF(入力!D31="","","("&入力!D31&"泊)")) | D16: =IF(入力!A31="","",入力!C31) | E16: =IF(OR(入力!A31="",COUNT(入力!B31,入力!D31)<2),"",入力!B31*入力!D31) | F16: =IF(入力!A31="","","室") | G16: =IF(入力!E31="","",入力!E31)
A17: =IF(入力!A32="","",ROW()-15) | B17: =IF(入力!A32="","","宿泊") | C17: =IF(入力!A32="","",入力!A32&IF(入力!D32="","","("&入力!D32&"泊)")) | D17: =IF(入力!A32="","",入力!C32) | E17: =IF(OR(入力!A32="",COUNT(入力!B32,入力!D32)<2),"",入力!B32*入力!D32) | F17: =IF(入力!A32="","","室") | G17: =IF(入力!E32="","",入力!E32)
A18: =IF(入力!A33="","",ROW()-15) | B18: =IF(入力!A33="","","宿泊") | C18: =IF(入力!A33="","",入力!A33&IF(入力!D33="","","("&入力!D33&"泊)")) | D18: =IF(入力!A33="","",入力!C33) | E18: =IF(OR(入力!A33="",COUNT(入力!B33,入力!D33)<2),"",入力!B33*入力!D33) | F18: =IF(入力!A33="","","室") | G18: =IF(入力!E33="","",入力!E33)
A19: =IF(入力!A34="","",ROW()-15) | B19: =IF(入力!A34="","","宿泊") | C19: =IF(入力!A34="","",入力!A34&IF(入力!D34="","","("&入力!D34&"泊)")) | D19: =IF(入力!A34="","",入力!C34) | E19: =IF(OR(入力!A34="",COUNT(入力!B34,入力!D34)<2),"",入力!B34*入力!D34) | F19: =IF(入力!A34="","","室") | G19: =IF(入力!E34="","",入力!E34)
A20: =IF(入力!A35="","",ROW()-15) | B20: =IF(入力!A35="","","宿泊") | C20: =IF(入力!A35="","",入力!A35&IF(入力!D35="","","("&入力!D35&"泊)")) | D20: =IF(入力!A35="","",入力!C35) | E20: =IF(OR(入力!A35="",COUNT(入力!B35,入力!D35)<2),"",入力!B35*入力!D35) | F20: =IF(入力!A35="","","室") | G20: =IF(入力!E35="","",入力!E35)
A21: =IF(入力!A36="","",ROW()-15) | B21: =IF(入力!A36="","","宿泊") | C21: =IF(入力!A36="","",入力!A36&IF(入力!D36="","","("&入力!D36&"泊)")) | D21: =IF(入力!A36="","",入力!C36) | E21: =IF(OR(入力!A36="",COUNT(入力!B36,入力!D36)<2),"",入力!B36*入力!D36) | F21: =IF(入力!A36="","","室") | G21: =IF(入力!E36="","",入力!E36)
A22: =IF(入力!A37="","",ROW()-15) | B22: =IF(入力!A37="","","宿泊") | C22: =IF(入力!A37="","",入力!A37&IF(入力!D37="","","("&入力!D37&"泊)")) | D22: =IF(入力!A37="","",入力!C37) | E22: =IF(OR(入力!A37="",COUNT(入力!B37,入力!D37)<2),"",入力!B37*入力!D37) | F22: =IF(入力!A37="","","室") | G22: =IF(入力!E37="","",入力!E37)
A23: =IF(入力!A38="","",ROW()-15) | B23: =IF(入力!A38="","","宿泊") | C23: =IF(入力!A38="","",入力!A38&IF(入力!D38="","","("&入力!D38&"泊)")) | D23: =IF(入力!A38="","",入力!C38) | E23: =IF(OR(入力!A38="",COUNT(入力!B38,入力!D38)<2),"",入力!B38*入力!D38) | F23: =IF(入力!A38="","","室") | G23: =IF(入力!E38="","",入力!E38)
A24: =IF(入力!B69="","",ROW()-23) | B24: =IF(入力!A69="","",入力!A69) | C24: =IF(入力!B69="","",入力!B69) | D24: =IF(入力!C69="","",入力!C69) | E24: =IF(入力!D69="","",入力!D69) | F24: =IF(入力!E69="","",入力!E69) | G24: =IF(COUNT(入力!C69,入力!D69)<2,"",入力!C69*入力!D69)
A25: =IF(入力!B70="","",ROW()-23) | B25: =IF(入力!A70="","",入力!A70) | C25: =IF(入力!B70="","",入力!B70) | D25: =IF(入力!C70="","",入力!C70) | E25: =IF(入力!D70="","",入力!D70) | F25: =IF(入力!E70="","",入力!E70) | G25: =IF(COUNT(入力!C70,入力!D70)<2,"",入力!C70*入力!D70)
A26: =IF(入力!B71="","",ROW()-23) | B26: =IF(入力!A71="","",入力!A71) | C26: =IF(入力!B71="","",入力!B71) | D26: =IF(入力!C71="","",入力!C71) | E26: =IF(入力!D71="","",入力!D71) | F26: =IF(入力!E71="","",入力!E71) | G26: =IF(COUNT(入力!C71,入力!D71)<2,"",入力!C71*入力!D71)
A27: =IF(入力!B72="","",ROW()-23) | B27: =IF(入力!A72="","",入力!A72) | C27: =IF(入力!B72="","",入力!B72) | D27: =IF(入力!C72="","",入力!C72) | E27: =IF(入力!D72="","",入力!D72) | F27: =IF(入力!E72="","",入力!E72) | G27: =IF(COUNT(入力!C72,入力!D72)<2,"",入力!C72*入力!D72)
A28: =IF(入力!B73="","",ROW()-23) | B28: =IF(入力!A73="","",入力!A73) | C28: =IF(入力!B73="","",入力!B73) | D28: =IF(入力!C73="","",入力!C73) | E28: =IF(入力!D73="","",入力!D73) | F28: =IF(入力!E73="","",入力!E73) | G28: =IF(COUNT(入力!C73,入力!D73)<2,"",入力!C73*入力!D73)
A29: =IF(入力!B74="","",ROW()-23) | B29: =IF(入力!A74="","",入力!A74) | C29: =IF(入力!B74="","",入力!B74) | D29: =IF(入力!C74="","",入力!C74) | E29: =IF(入力!D74="","",入力!D74) | F29: =IF(入力!E74="","",入力!E74) | G29: =IF(COUNT(入力!C74,入力!D74)<2,"",入力!C74*入力!D74)
A30: =IF(入力!B75="","",ROW()-23) | B30: =IF(入力!A75="","",入力!A75) | C30: =IF(入力!B75="","",入力!B75) | D30: =IF(入力!C75="","",入力!C75) | E30: =IF(入力!D75="","",入力!D75) | F30: =IF(入力!E75="","",入力!E75) | G30: =IF(COUNT(入力!C75,入力!D75)<2,"",入力!C75*入力!D75)
A31: =IF(入力!B76="","",ROW()-23) | B31: =IF(入力!A76="","",入力!A76) | C31: =IF(入力!B76="","",入力!B76) | D31: =IF(入力!C76="","",入力!C76) | E31: =IF(入力!D76="","",入力!D76) | F31: =IF(入力!E76="","",入力!E76) | G31: =IF(COUNT(入力!C76,入力!D76)<2,"",入力!C76*入力!D76)
A32: =IF(入力!B77="","",ROW()-23) | B32: =IF(入力!A77="","",入力!A77) | C32: =IF(入力!B77="","",入力!B77) | D32: =IF(入力!C77="","",入力!C77) | E32: =IF(入力!D77="","",入力!D77) | F32: =IF(入力!E77="","",入力!E77) | G32: =IF(COUNT(入力!C77,入力!D77)<2,"",入力!C77*入力!D77)
A33: =IF(入力!B78="","",ROW()-23) | B33: =IF(入力!A78="","",入力!A78) | C33: =IF(入力!B78="","",入力!B78) | D33: =IF(入力!C78="","",入力!C78) | E33: =IF(入力!D78="","",入力!D78) | F33: =IF(入力!E78="","",入力!E78) | G33: =IF(COUNT(入力!C78,入力!D78)<2,"",入力!C78*入力!D78)
D34: 小計 | G34: =SUM(G16:G33) -> 0
D35: サービス料(10%) | G35: =ROUND(G34*0.1,0) -> 0
D36: 消費税(10%) | G36: =ROUND((G34+G35)*0.1,0) -> 0
A37: ※入湯税=150円×宿泊人数×泊数(入力シートで) | D37: 入湯税 | G37: =N(入力!B79) -> 0
D38: お値引き | G38: =N(入力!B80) -> 0
D39: 御見積合計(税込) | G39: =G34+G35+G36+G37+G38 -> 0
A41: 備考

Sheet 請求書
B1: 御 請 求 書 | F1: 請求番号 | G1: =IF(入力!B87="","",SUBSTITUTE(入力!B87,"Q-","I-"))
F2: 請求日
F3: ブロックコード | G3: =IF(入力!B86="","",入力!B86)
A4: =IF(入力!B5="","",入力!B5&" 御中") | F4: 【ロゴ】
A5: =IF(入力!B6="","",入力!B6)
A6: =IF(入力!B7="","",入力!B7) | F6: =マスタ!I2 -> (ホテル名を入力)
A7: =IF(入力!B10="","","ご担当: "&入力!B10) | F7: =マスタ!I3 -> (住所・TELを入力)
A8: 下記のとおりご請求申し上げます。 | F8: ="インボイス登録番号 "&マスタ!I4 -> インボイス登録番号 T0000000000000
F9: 担当: | G9: =マスタ!I5 -> 0
A10: 件名 | C10: =IF(入力!B7<>"",入力!B7,IF(入力!B6<>"",入力!B6,IF(入力!B5="","",入力!B5&"様"))) | F10: 御請求合計(税込)
A11: ご利用期間 | C11: =IF(入力!B14="","",TEXT(入力!B14,"yyyy/m/d")&" 〜 "&IF(入力!B15="","",TEXT(入力!B15,"m/d"))) | F11: =G31
A12: ご利用人数 | C12: =IF(入力!B24="","",入力!B24&"名(大人"&N(入力!B21)&"・子供"&N(入力!B22)&"・添乗員"&N(入力!B23)&")")
A13: お支払方法 | C13: =IF(入力!B64="","",入力!B64) | F13: お支払期日
A15: No. | B15: 項目 | C15: 内容 | D15: 単価 | E15: 数量 | F15: 単位 | G15: 金額
A16: =IF(入力!A31="","",ROW()-15) | B16: =IF(入力!A31="","","宿泊") | C16: =IF(入力!A31="","",入力!A31&IF(入力!D31="","","("&入力!D31&"泊)")) | D16: =IF(入力!A31="","",入力!C31) | E16: =IF(OR(入力!A31="",COUNT(入力!B31,入力!D31)<2),"",入力!B31*入力!D31) | F16: =IF(入力!A31="","","室") | G16: =IF(入力!E31="","",入力!E31)
A17: =IF(入力!A32="","",ROW()-15) | B17: =IF(入力!A32="","","宿泊") | C17: =IF(入力!A32="","",入力!A32&IF(入力!D32="","","("&入力!D32&"泊)")) | D17: =IF(入力!A32="","",入力!C32) | E17: =IF(OR(入力!A32="",COUNT(入力!B32,入力!D32)<2),"",入力!B32*入力!D32) | F17: =IF(入力!A32="","","室") | G17: =IF(入力!E32="","",入力!E32)
A18: =IF(入力!A33="","",ROW()-15) | B18: =IF(入力!A33="","","宿泊") | C18: =IF(入力!A33="","",入力!A33&IF(入力!D33="","","("&入力!D33&"泊)")) | D18: =IF(入力!A33="","",入力!C33) | E18: =IF(OR(入力!A33="",COUNT(入力!B33,入力!D33)<2),"",入力!B33*入力!D33) | F18: =IF(入力!A33="","","室") | G18: =IF(入力!E33="","",入力!E33)
A19: =IF(入力!A34="","",ROW()-15) | B19: =IF(入力!A34="","","宿泊") | C19: =IF(入力!A34="","",入力!A34&IF(入力!D34="","","("&入力!D34&"泊)")) | D19: =IF(入力!A34="","",入力!C34) | E19: =IF(OR(入力!A34="",COUNT(入力!B34,入力!D34)<2),"",入力!B34*入力!D34) | F19: =IF(入力!A34="","","室") | G19: =IF(入力!E34="","",入力!E34)
A20: =IF(入力!A35="","",ROW()-15) | B20: =IF(入力!A35="","","宿泊") | C20: =IF(入力!A35="","",入力!A35&IF(入力!D35="","","("&入力!D35&"泊)")) | D20: =IF(入力!A35="","",入力!C35) | E20: =IF(OR(入力!A35="",COUNT(入力!B35,入力!D35)<2),"",入力!B35*入力!D35) | F20: =IF(入力!A35="","","室") | G20: =IF(入力!E35="","",入力!E35)
A21: =IF(入力!A36="","",ROW()-15) | B21: =IF(入力!A36="","","宿泊") | C21: =IF(入力!A36="","",入力!A36&IF(入力!D36="","","("&入力!D36&"泊)")) | D21: =IF(入力!A36="","",入力!C36) | E21: =IF(OR(入力!A36="",COUNT(入力!B36,入力!D36)<2),"",入力!B36*入力!D36) | F21: =IF(入力!A36="","","室") | G21: =IF(入力!E36="","",入力!E36)
A22: =IF(入力!A37="","",ROW()-15) | B22: =IF(入力!A37="","","宿泊") | C22: =IF(入力!A37="","",入力!A37&IF(入力!D37="","","("&入力!D37&"泊)")) | D22: =IF(入力!A37="","",入力!C37) | E22: =IF(OR(入力!A37="",COUNT(入力!B37,入力!D37)<2),"",入力!B37*入力!D37) | F22: =IF(入力!A37="","","室") | G22: =IF(入力!E37="","",入力!E37)
A23: =IF(入力!A38="","",ROW()-15) | B23: =IF(入力!A38="","","宿泊") | C23: =IF(入力!A38="","",入力!A38&IF(入力!D38="","","("&入力!D38&"泊)")) | D23: =IF(入力!A38="","",入力!C38) | E23: =IF(OR(入力!A38="",COUNT(入力!B38,入力!D38)<2),"",入力!B38*入力!D38) | F23: =IF(入力!A38="","","室") | G23: =IF(入力!E38="","",入力!E38)
A24: =IF(入力!B69="","",ROW()-23) | B24: =IF(入力!A69="","",入力!A69) | C24: =IF(入力!B69="","",入力!B69) | D24: =IF(入力!C69="","",入力!C69) | E24: =IF(入力!D69="","",入力!D69) | F24: =IF(入力!E69="","",入力!E69) | G24: =IF(COUNT(入力!C69,入力!D69)<2,"",入力!C69*入力!D69)
A25: =IF(入力!B70="","",ROW()-23) | B25: =IF(入力!A70="","",入力!A70) | C25: =IF(入力!B70="","",入力!B70) | D25: =IF(入力!C70="","",入力!C70) | E25: =IF(入力!D70="","",入力!D70) | F25: =IF(入力!E70="","",入力!E70) | G25: =IF(COUNT(入力!C70,入力!D70)<2,"",入力!C70*入力!D70)
A26: =IF(入力!B71="","",ROW()-23) | B26: =IF(入力!A71="","",入力!A71) | C26: =IF(入力!B71="","",入力!B71) | D26: =IF(入力!C71="","",入力!C71) | E26: =IF(入力!D71="","",入力!D71) | F26: =IF(入力!E71="","",入力!E71) | G26: =IF(COUNT(入力!C71,入力!D71)<2,"",入力!C71*入力!D71)
A27: =IF(入力!B72="","",ROW()-23) | B27: =IF(入力!A72="","",入力!A72) | C27: =IF(入力!B72="","",入力!B72) | D27: =IF(入力!C72="","",入力!C72) | E27: =IF(入力!D72="","",入力!D72) | F27: =IF(入力!E72="","",入力!E72) | G27: =IF(COUNT(入力!C72,入力!D72)<2,"",入力!C72*入力!D72)
A28: =IF(入力!B73="","",ROW()-23) | B28: =IF(入力!A73="","",入力!A73) | C28: =IF(入力!B73="","",入力!B73) | D28: =IF(入力!C73="","",入力!C73) | E28: =IF(入力!D73="","",入力!D73) | F28: =IF(入力!E73="","",入力!E73) | G28: =IF(COUNT(入力!C73,入力!D73)<2,"",入力!C73*入力!D73)
A29: =IF(入力!B74="","",ROW()-23) | B29: =IF(入力!A74="","",入力!A74) | C29: =IF(入力!B74="","",入力!B74) | D29: =IF(入力!C74="","",入力!C74) | E29: =IF(入力!D74="","",入力!D74) | F29: =IF(入力!E74="","",入力!E74) | G29: =IF(COUNT(入力!C74,入力!D74)<2,"",入力!C74*入力!D74)
A30: =IF(入力!B75="","",ROW()-23) | B30: =IF(入力!A75="","",入力!A75) | C30: =IF(入力!B75="","",入力!B75) | D30: =IF(入力!C75="","",入力!C75) | E30: =IF(入力!D75="","",入力!D75) | F30: =IF(入力!E75="","",入力!E75) | G30: =IF(COUNT(入力!C75,入力!D75)<2,"",入力!C75*入力!D75)
A31: =IF(入力!B76="","",ROW()-23) | B31: =IF(入力!A76="","",入力!A76) | C31: =IF(入力!B76="","",入力!B76) | D31: =IF(入力!C76="","",入力!C76) | E31: =IF(入力!D76="","",入力!D76) | F31: =IF(入力!E76="","",入力!E76) | G31: =IF(COUNT(入力!C76,入力!D76)<2,"",入力!C76*入力!D76)
A32: =IF(入力!B77="","",ROW()-23) | B32: =IF(入力!A77="","",入力!A77) | C32: =IF(入力!B77="","",入力!B77) | D32: =IF(入力!C77="","",入力!C77) | E32: =IF(入力!D77="","",入力!D77) | F32: =IF(入力!E77="","",入力!E77) | G32: =IF(COUNT(入力!C77,入力!D77)<2,"",入力!C77*入力!D77)
A33: =IF(入力!B78="","",ROW()-23) | B33: =IF(入力!A78="","",入力!A78) | C33: =IF(入力!B78="","",入力!B78) | D33: =IF(入力!C78="","",入力!C78) | E33: =IF(入力!D78="","",入力!D78) | F33: =IF(入力!E78="","",入力!E78) | G33: =IF(COUNT(入力!C78,入力!D78)<2,"",入力!C78*入力!D78)
D34: 小計 | G34: =SUM(G16:G33) -> 0
D35: サービス料(10%) | G35: =ROUND(G34*0.1,0) -> 0
D36: 消費税(10%) | G36: =ROUND((G34+G35)*0.1,0) -> 0
A37: ※入湯税=150円×宿泊人数×泊数(入力シートで) | D37: 入湯税 | G37: =N(入力!B79) -> 0
D38: お値引き | G38: =N(入力!B80) -> 0
D39: 御請求合計(税込) | G39: =G34+G35+G36+G37+G38 -> 0
A41: お振込先 | B41: =マスタ!I6 -> (銀行名・支店・口座種別・番号・名義)
A42: 備考

Sheet 領収書
F1: 領収書No. | G1: =IF(入力!B87="","",SUBSTITUTE(入力!B87,"Q-","R-"))
B2: 領 収 書 | F2: 発行日
A5: =IF(入力!B5="","",入力!B5&" 御中")
A6: =IF(入力!B6="","",入力!B6)
B8: =IF(見積書!G39=0,"","¥ "&TEXT(見積書!G39,"#,##0")&" −")
A11: 但し | F11: (例: ご宿泊・ご宴会代として)
A12: 上記の金額を正に領収いたしました。
F13: 収 入 印 紙
A14: 内訳 | B14: 税込合計 | C14: =IF(見積書!G39=0,"",見積書!G39)
B15: うち消費税 | C15: =IF(見積書!G36="","",見積書!G36) -> 0
A18: =マスタ!I2 -> (ホテル名を入力)
A19: =マスタ!I3 -> (住所・TELを入力)
A20: ="インボイス登録番号 "&マスタ!I4 -> インボイス登録番号 T0000000000000

Sheet 工程表
A1: イベント工程表 | D1: ブロックコード | E1: =IF(入力!B86="","",入力!B86)
A2: =IF(入力!B7<>"",入力!B7,入力!B6)&IF(入力!B24="",""," "&入力!B24&"名") | D2: 日程 | E2: =IF(入力!B14="","",TEXT(入力!B14,"m/d")&"〜"&TEXT(入力!B15,"m/d"))
A4: 時刻 | B4: 内容 | C4: 場所 | D4: 担当 | E4: 備考
B5: =IF(入力!B58="","","[往路送迎] "&入力!B58)
B6: =IF(入力!B16="","","[到着] "&入力!B16)
B7: =IF(OR(入力!B18="",入力!B18="なし"),"","[お出迎え・挨拶] "&入力!B18&" "&入力!B19)
B8: =IF(入力!B27="","","[チェックイン] "&入力!B27)
B9: =IF(入力!B53="","","[会場設営〜撤収] "&入力!B53) | C9: =IF(入力!B52="","",入力!B52)
B10: =IF(AND(入力!B44="",入力!C44="",入力!D44=""),"","[食事] "&入力!A44&" "&入力!D44&" "&入力!C44&" "&入力!B44)
B11: =IF(AND(入力!B45="",入力!C45="",入力!D45=""),"","[食事] "&入力!A45&" "&入力!D45&" "&入力!C45&" "&入力!B45)
B12: =IF(AND(入力!B46="",入力!C46="",入力!D46=""),"","[食事] "&入力!A46&" "&入力!D46&" "&入力!C46&" "&入力!B46)
B13: =IF(AND(入力!B47="",入力!C47="",入力!D47=""),"","[食事] "&入力!A47&" "&入力!D47&" "&入力!C47&" "&入力!B47)
B14: =IF(AND(入力!B48="",入力!C48="",入力!D48=""),"","[食事] "&入力!A48&" "&入力!D48&" "&入力!C48&" "&入力!B48)
B15: =IF(AND(入力!B49="",入力!C49="",入力!D49=""),"","[食事] "&入力!A49&" "&入力!D49&" "&入力!C49&" "&入力!B49)
B16: =IF(入力!B56="","","[進行] "&入力!B56)
B17: =IF(入力!B28="","","[チェックアウト] "&入力!B28)
B18: =IF(入力!B59="","","[復路送迎] "&入力!B59)
B19: =IF(入力!B17="","","[出発] "&入力!B17)
A29: ※[ ]付きの行は入力シートから自動。時刻・担当を書き足し、行が足りなければ下の空行へ。

Sheet 館内案内アライ
A3: フロント内線 ０番 | Y3: ホテル公式HP
A5: ● ご夕食 | E5: (90分制)
A7: 日付 | E7: 店舗名 | P7: 場所 | V7: 営業時間
A8: ='New Booking Sheet'!D8 -> 46217 | E8: 洋食ビュッフェ 「The・Plate」 | P8: アライ棟1F | V8: ='New Booking Sheet'!D8 -> 46217 | AD8: (90分制)
AH9: ← 1泊の場合は非表示！！
A10: ● ご朝食 | E10: (60分制)
A11: 日付 | E11: 店舗名 | P11: 場所 | V11: 営業時間
A12: =A8+1 -> 46218 | E12: 洋食ビュッフェ 「The・Plate」 | P12: アライ棟1F | V12: 07:00〜10:00 (L.O. 09:30) | AH12: ← 1店舗営業の場合は非表示！！
E13: 和食ビュッフェ 「あさ日」 | P13: ロッジ棟2F
A16: ● 温泉 | G16: タオルのご利用については、お部屋よりお持ちください。
G17: なお温泉受付でのタオルの貸し出しはバスタオル・フェイスタオルの二枚組 200円(税込)です。
G18: ※05:00-13:00の間は温泉受付スタッフ不在につき、タオルの貸し出しは出来かねます。
A20: 店舗名 | F20: 場所 | L20: 曜日 | T20: 営業時間
A21: 「星空温泉」 | F21: アライ棟2F | L21: 平日 | T21: 05:00〜10:00 (最終入場 09:30) 13:00〜23:00 (最終入場 22:30)
L22: 土曜日・日曜日・祝日 | T22: 05:00〜23:00 (最終入場 22:30)
A25: ● 売店
A27: 店舗名 | K27: 場所 | V27: 営業時間
A28: 特産品ショップ 「六花」 | K28: アライ棟B1F - ロッジ棟1F (屋外連絡通路) | V28: 09:00〜21:00
A29: 無人コンビニ | K29: アライ棟B1F | V29: 24時間営業
A32: ●客室案内
A34: 会員登録 | G34: 会員特典 : ①対象レストラン5%割引 ②500ポイント(5$)付与
G35: ポイントはお土産など、施設利用にご利用いただけます。フロントにて簡単にご登録いただけます。
A36: アメニティ | G36: アライ棟1F ロビーのアメニティデスクよりご自由にお持ちください。 | AH36: ← ロッジ宿泊の場合は非表示！！
A38: 館内のご移動 について | G38: 温泉・プールご利用の際は浴衣とスリッパをご着用いただけます。
G39: レストラン等その他の施設は私服とお靴をご着用のうえでご利用ください。
G40: ※時期により床が滑りやすくなっておりますので、スリッパでのご移動は十分ご注意ください。
A41: ミネラルウォーター | G41: 冷蔵庫内に1泊につきご宿泊人数分の無料のミネラルウォーターをご用意しております。
A42: 自動販売機 | G42: （ソフトドリンク） | L42: ①ロッジ棟2F ②アライ棟2F 星空温泉内 ③ヴィレッジステーション1F
G43: （アイス） | L43: アライ棟2F 星空温泉内
G44: （アルコール） | L44: ロッジ棟2F
A45: 電子レンジ | G45: (アライ棟) | L45: B1F セルフコンビニ横
G46: (ロッジ棟) | L46: 2F ランドリールーム
A47: 製氷機 | G47: （アライ棟） | L47: 3F 客室フロア、4F 客室フロア
G48: （ロッジ棟） | L48: 2F ランドリールーム
A49: 喫煙所 | G49: ①アライ棟B1F - ロッジ棟1F(屋外連絡通路)のランドリー前 ②ロッジ棟B1Fエントランス脇
G50: ※バルコニー含む客室内での喫煙はご遠慮ください。
A51: ルームキー | G51: 紛失した場合は交換費用として30,000円を頂戴しますのでご注意ください。 | AH51: ← アライ宿泊の場合は非表示！！
G52: 外出の際はフロントデスクにてお預かりいたします。
A54: ◎ Free Wi-Fi | F54: 右のQRコードをスマートフォンで読み取っていただければ接続できます。
B55: SSID ： Lotte Arai Resort
B56: パスワード ： arai1429

Sheet 館内案内ロッジ
A3: フロント内線 ０番 | Y3: ホテル公式HP
A5: ● ご夕食 | E5: (90分制)
A7: 日付 | E7: 店舗名 | P7: 場所 | V7: 営業時間
A8: ='New Booking Sheet'!D8 -> 46217 | E8: 洋食ビュッフェ 「The・Plate」 | P8: アライ棟1F | V8: ='New Booking Sheet'!D8 -> 46217 | AD8: (90分制)
AH9: ← 1泊の場合は非表示！！
A10: ● ご朝食 | E10: (60分制)
A11: 日付 | E11: 店舗名 | P11: 場所 | V11: 営業時間
A12: =A8+1 -> 46218 | E12: 洋食ビュッフェ 「The・Plate」 | P12: アライ棟1F | V12: 07:00〜10:00 (L.O. 09:30) | AH12: ← 1店舗営業の場合は非表示！！
E13: 和食ビュッフェ 「あさ日」 | P13: ロッジ棟2F
A16: ● 温泉 | G16: タオルのご利用については、お部屋よりお持ちください。
G17: なお温泉受付でのタオルの貸し出しはバスタオル・フェイスタオルの二枚組 200円(税込)です。
G18: ※05:00-13:00の間は温泉受付スタッフ不在につき、タオルの貸し出しは出来かねます。
A20: 店舗名 | F20: 場所 | L20: 曜日 | T20: 営業時間
A21: 「星空温泉」 | F21: アライ棟2F | L21: 平日 | T21: 05:00〜10:00 (最終入場 09:30) 13:00〜23:00 (最終入場 22:30)
L22: 土曜日・日曜日・祝日 | T22: 05:00〜23:00 (最終入場 22:30)
A25: ● 売店
A27: 店舗名 | K27: 場所 | V27: 営業時間
A28: 特産品ショップ 「六花」 | K28: アライ棟B1F - ロッジ棟1F (屋外連絡通路) | V28: 09:00〜21:00
A29: 無人コンビニ | K29: アライ棟B1F | V29: 24時間営業
A32: ●客室案内
A34: 会員登録 | G34: 会員特典 : ①対象レストラン5%割引 ②500ポイント(5$)付与
G35: ポイントはお土産など、施設利用にご利用いただけます。フロントにて簡単にご登録いただけます。
A36: アメニティ | G36: アライ棟1F ロビーのアメニティデスクよりご自由にお持ちください。 | AH36: ← ロッジ宿泊の場合は非表示！！
A38: 館内のご移動 について | G38: 温泉・プールご利用の際は浴衣とスリッパをご着用いただけます。
G39: レストラン等その他の施設は私服とお靴をご着用のうえでご利用ください。
G40: ※時期により床が滑りやすくなっておりますので、スリッパでのご移動は十分ご注意ください。
A41: ミネラルウォーター | G41: 冷蔵庫内に1泊につきご宿泊人数分の無料のミネラルウォーターをご用意しております。
A42: 自動販売機 | G42: （ソフトドリンク） | L42: ①ロッジ棟2F ②アライ棟2F 星空温泉内 ③ヴィレッジステーション1F
G43: （アイス） | L43: アライ棟2F 星空温泉内
G44: （アルコール） | L44: ロッジ棟2F
A45: 電子レンジ | G45: (アライ棟) | L45: B1F セルフコンビニ横
G46: (ロッジ棟) | L46: 2F ランドリールーム
A47: 製氷機 | G47: （アライ棟） | L47: 3F 客室フロア、4F 客室フロア
G48: （ロッジ棟） | L48: 2F ランドリールーム
A49: 喫煙所 | G49: ①アライ棟B1F - ロッジ棟1F(屋外連絡通路)のランドリー前 ②ロッジ棟B1Fエントランス脇
G50: ※バルコニー含む客室内での喫煙はご遠慮ください。
A51: ルームキー | G51: 紛失した場合は交換費用として30,000円を頂戴しますのでご注意ください。 | AH51: ← アライ宿泊の場合は非表示！！
G52: 外出の際はフロントデスクにてお預かりいたします。
A54: ◎ Free Wi-Fi | F54: 右のQRコードをスマートフォンで読み取っていただければ接続できます。
B55: SSID ： Lotte Arai Resort
B56: パスワード ： arai1429

Sheet FAX送付状
A2: Fax 送付状
E4: 送信日： | F4: =TODAY() -> 46221
E5: 送信枚数： | F5: 本紙含め 2枚
A7: 送付先 | E7: 差出人
A8: 株式会社 | C8: 御中 | E8: ロッテアライリゾート
A9: 添乗員 | C9: 様 | E9: 宿泊課
A10: TEL： | E10: TEL：0255-75-1103
A11: FAX： | E11: FAX：0255-75-1157

Sheet マスタ
A1: ステータス | B1: 支払方法 | C1: 会場 | D1: レイアウト | E1: 明細項目 | F1: 単位 | G1: 確度 | H1: ▼ホテル情報・設定(帳票の発行者欄などに入ります) | J1: 時刻(15分毎) | K1: 食事会場
A2: 引合 | B2: 未定 | C2: 宴会場 | D2: シアター | E2: 宿泊 | F2: 名 | G2: S | H2: ホテル名 | I2: (ホテル名を入力) | J2: 6:30 | K2: ザ・プレート
A3: 仮予約 | B3: 現地支払 | C3: 多目的ホール | D3: スクール | E3: 宴会 | F3: 式 | G3: A | H3: 住所・TEL | I3: (住所・TELを入力) | J3: 6:45 | K3: あさ日
A4: 確定 | B4: 事前振込 | C4: ザ・プレート | D4: 円卓 | E4: 料飲 | F4: 台 | G4: B | H4: インボイス番号 | I4: T0000000000000 | J4: 7:00 | K4: 矢代
A5: 実施済 | B5: 売掛 | C5: あさ日 | D5: 立食 | E5: 送迎 | F5: 室 | G5: C | H5: 担当者 | J5: 7:15 | K5: BECO
A6: 請求済 | C6: BECO | E6: その他 | F6: 個 | H6: 振込先 | I6: (銀行名・支店・口座種別・番号・名義) | J6: 7:30
A7: 入金済 | C7: 矢代 | F7: 本 | J7: 7:45
A8: キャンセル | H8: カレンダーURL | J8: 8:00
J9: 8:15
J10: 8:30
A11: 選択肢はこの列を書き換えれば入力シートの▼リストに反映。カレンダーURL(I8)を入れると入力シートのリンクが有効になります。 | J11: 8:45
J12: 9:00
J13: 9:15
J14: 9:30
J15: 9:45
J16: 10:00
J17: 10:15
J18: 10:30
J19: 10:45
J20: 11:00
J21: 11:15
J22: 11:30
J23: 11:45
... J60: 21:00

Sheet 食事PKG
A2: 2026 F＆B PackageCode
A3: セグメント | B3: 区分 | D3: SNOW （2026-05-10まで） | J3: GREEN （2026-05-11から）
D4: RATECODE | E4: 金額(net) | F4: 金額(サ込) | G4: 割引率 | H4: 前年比 | I4: Description | J4: RATECODE | K4: 金額(net) | L4: 金額(サ込) | M4: 割引率 | N4: 前年比 | O4: Description
A5: (A) | B5: 大人 | C5: 朝食 | D5: BFAS-A | E5: 4000 | F5: 4400 | H5: 1 | I5: New BF Adult Snow - A rank - 4000 | J5: BFAG-A | K5: 3200 | L5: 3520 | N5: 0.8 | O5: New BF Adult Green - A rank - 3200
A6: 定価料金/日帰り 宿泊者当日追加料金 | C6: 夕食 | D6: DNAS-A | E6: 6300 | F6: 6930 | H6: 1.0862069 | I6: New DN Adult Snow - A rank - 6300 | J6: DNAG-A | K6: 4800 | L6: 5280 | N6: 0.82758621 | O6: New DN Adult Green - A rank - 4800
B7: 子供 4-12 | C7: 朝食 | D7: BFKS-A | E7: 2400 | F7: 2640 | H7: 1.0909091 | I7: New BF Child Snow - A rank - 2400 | J7: BFKG-A | K7: 2000 | L7: 2200 | N7: 0.90909091 | O7: New BF Child Green - A rank - 2000
C8: 夕食 | D8: DNKS-A | E8: 3500 | F8: 3850 | H8: 0.94594595 | I8: New DN Child Snow - A rank - 3500 | J8: DNKG-A | K8: 3000 | L8: 3300 | N8: 0.81081081 | O8: New DN Child Green - A rank - 3000
A9: (B) | B9: 大人 | C9: 朝食 | D9: BFAS-B | E9: 3500 | F9: 3850 | G9: 0.875 | H9: 0.96418733 | I9: New BF Adult Snow - B rank - 3500 | J9: BFAG-B | K9: 2800 | L9: 3080 | M9: 0.875 | N9: 0.77134986 | O9: New BF Adult Green - B rank - 2800
A10: 一般宿泊PKG 全店舗利用可能 | C10: 夕食 | D10: DNAS-B | E10: 5200 | F10: 5720 | G10: 0.82539683 | H10: 0.98484848 | I10: New DN Adult Snow - B rank - 5200 | J10: DNAG-B | K10: 4000 | L10: 4400 | M10: 0.83333333 | N10: 0.75757576 | O10: New DN Adult Green - B rank - 4000
B11: 子供 4-12 | C11: 朝食 | D11: BFKS-B | E11: 2000 | F11: 2200 | G11: 0.83333333 | H11: 1.0695187 | I11: New BF Child Snow - B rank - 2000 | J11: BFKG-B | K11: 1700 | L11: 1870 | M11: 0.85 | N11: 0.90909091 | O11: New BF Child Green - B rank - 1700
C12: 夕食 | D12: DNKS-B | E12: 3000 | F12: 3300 | G12: 0.85714286 | H12: 0.90909091 | I12: New DN Child Snow - B rank - 3000 | J12: DNKG-B | K12: 2500 | L12: 2750 | M12: 0.83333333 | N12: 0.75757576 | O12: New DN Child Green - B rank - 2500
A13: (C) | B13: 大人 | C13: 朝食 | D13: BFAS-C | E13: 3000 | F13: 3300 | G13: 0.75 | H13: 0.97402597 | I13: New BF Adult Snow - C rank - 3000 | J13: BFAG-C | K13: 2500 | L13: 2750 | M13: 0.78125 | N13: 0.81168831 | O13: New BF Adult Green - C rank - 2500
A14: 一般宿泊限定商品 | C14: 夕食 | D14: DNAS-C | E14: 4800 | F14: 5280 | G14: 0.76190476 | H14: 1 | I14: New DN Adult Snow - C rank - 4800 | J14: DNAG-C | K14: 3700 | L14: 4070 | M14: 0.77083333 | N14: 0.77083333 | O14: New DN Adult Green - C rank - 3700
B15: 子供 4-12 | C15: 朝食 | D15: BFKS-C | E15: 1700 | F15: 1870 | G15: 0.70833333 | H15: 1.1038961 | I15: New BF Child Snow - C rank - 1700 | J15: BFKG-C | K15: 1500 | L15: 1650 | M15: 0.75 | N15: 0.97402597 | O15: New BF Child Green - C rank - 1500
C16: 夕食 | D16: DNKS-C | E16: 2800 | F16: 3080 | G16: 0.8 | H16: 0.93333333 | I16: New DN Child Snow - C rank - 2800 | J16: DNKG-C | K16: 2100 | L16: 2310 | M16: 0.7 | N16: 0.7 | O16: New DN Child Green - C rank - 2100
A17: （D）団体、修学旅行特別 従業員特別、法人特別 稟議申請により特別適用可（直営店限定） | B17: 大人 | C17: 朝食 | D17: BFAS-D | E17: 2400 | F17: 2640 | G17: 0.6 | H17: 1.0909091 | I17: New BF Adult Snow - D rank - 2400 | J17: BFAG-D | K17: 2000 | L17: 2200 | M17: 0.625 | N17: 0.90909091 | O17: New BF Adult Green - D rank - 2000
C18: 夕食 | D18: DNAS-D | E18: 3500 | F18: 3850 | G18: 0.55555556 | H18: 0.8974359 | I18: New DN Adult Snow - D rank - 3500 | J18: DNAG-D | K18: 3000 | L18: 3300 | M18: 0.625 | N18: 0.76923077 | O18: New DN Adult Green - D rank - 3000
B19: 子供 4-12 | C19: 朝食 | D19: BFKS-D | E19: 1500 | F19: 1650 | G19: 0.625 | I19: New BF Child Snow - D rank - 1500 | J19: BFKG-D | K19: 1100 | L19: 1210 | M19: 0.55 | O19: New BF Child Green - D rank - 1100
C20: 夕食 | D20: DNKS-D | E20: 2500 | F20: 2750 | G20: 0.71428571 | I20: New DN Child Snow - D rank - 2500 | J20: DNKG-D | K20: 1650 | L20: 1815 | M20: 0.55 | O20: New DN Child Green - D rank - 1650

Sheet プルダウン　リスト
A2: 部屋タイプ | B2: 料金 | C2: 確度 | D2: 支払い方法 | E2: 税・サービス料 | F2: 朝食代 | G2: 朝食会場 | H2: 夕食代 | I2: 夕食予約時刻 | J2: 食事会場 | K2: 店舗名 | L2: 食事・入湯税 | M2: 追加精算
A3: -
A4: t/c, driver | B4: ご宿泊 | C4: S | D4: 未定 | E4: サ込税込 | F4: 1500 | G4: ザ・プレート | H4: 3000 | I4: - | J4: ザ・プレート | K4: 洋食ビュッフェ 「The Plate」 | L4: 別途 | M4: C/O時代表者一括清算
A5: Superior (Single Use) | B5: 1泊朝食付 | C5: A | D5: 現地支払 | E5: サ込税別 | F5: 2200 | G5: あさ日 | H5: 3900 | I5: 0.70833333 | J5: あさ日 | K5: 和食ビュッフェ 「あさ日」 | L5: 含む | M5: C/O時個人精算
A6: Superior Twin | B6: 1泊2食付 | C6: B | D6: 事前振込 | E6: 税サ別 | F6: 2800 | G6: あさ日・プレート | H6: 4800 | I6: 0.71875 | J6: BECO | K6: ステーキハウス「BECO」 | L6: なし | M6: 売掛
A7: Superior Double | C7: C | D7: 売掛 | I7: 0.72916667 | J7: 矢代 | K7: しゃぶしゃぶ 「矢代」 | M7: 備考参照
A8: Superior Family Twin | I8: 0.73958333
A9: Superior Triple | I9: 0.75
A10: Superior Family Triple | I10: 0.76041667
A11: Deluxe Double | I11: 0.77083333
A12: Deluxe Twin | I12: 0.78125
A13: Deluxe Twin (Single Use) | I13: 0.79166667
A14: Deluxe Family Twin | I14: 0.80208333
A15: Deluxe Double Twin | I15: 0.8125
A16: Deluxe Quadruple | I16: 0.82291667
A17: Deluxe Suite R | I17: 0.83333333
A18: Corner Suite
A19: Deluxe Suite
A20: Deluxe Suite F
A21: Premier Suite
A22: Grand Premier Suite
A23: Presidential Suite A
A24: Presidential Suite B
A25: Presidential Suite A＋B
G27: Fax 枚数
G28: 本紙のみ
G29: 本紙含め 2枚
G30: 本紙含め 3枚
G31: 本紙含め 4枚
G32: 本紙含め 5枚
G33: 本紙含め 6枚
G34: 本紙含め 7枚

Sheet New Booking Sheet
A1: 2026-070
S2: 日付 | U2: 46170
S3: 更新日 | Z3: 経理 | AA3: 郵送先 | AC3: 〒 | AP3: 宛名
S4: 現地 | U4: 手配 | W4: 営業
A5: 団体・ツアー名 | D5: =VLOOKUP(A1,'Group List(営業入力用)'!$A$1:$AT$925,7,0) -> JNC 韓国インバウンドツアー | S5: Koike | U5: Miyamoto | W5: Koike | AP5: 郵送
A6: 到着時刻 | C6: 0.66666667 | F6: 出発時刻 | L6: 国籍 | N6: =VLOOKUP(A1,'Group List(営業入力用)'!$A$1:$AT$925,15,0) -> Korea | Q6: Tour Number | T6: =VLOOKUP(A1,'Group List(営業入力用)'!$A$1:$AT$925,21,0) -> 0 | AA6: 項目 | AF6: 金額 | AH6: 人数 | AJ6: 泊数(数量) | AL6: 計 | AP6: 送付期日
A7: 概要 | D7: =VLOOKUP(A1,'Group List(営業入力用)'!$A$1:$AT$925,8,0) -> インバウンドツアー | P7: 人数 | Q7: =VLOOKUP(A1,'Group List(営業入力用)'!$A$1:$AT$925,20,0) -> 9 | S7: 添乗員 Driver | T7: =VLOOKUP(A1,'Group List(営業入力用)'!$A$1:$AT$925,17,0)+VLOOKUP(A1,'Group List(営業入力用)'!$A$1:$AT$925,18,0) -> 1 | V7: Status | W7: =VLOOKUP(A1,'Group List(営業入力用)'!$A$1:$AT$925,4,0) -> 仮予約 | AA7: ツイン１泊夕朝付 | AF7: 13680 | AJ7: 3 | AL7: =AF7*AH7*AJ7 -> 0 | AO7: シングル
A8: C/I | D8: =VLOOKUP(A1,'Group List(営業入力用)'!$A$1:$AT$925,2,0) -> 46217 | H8: 火 | I8: C/O | L8: =VLOOKUP(A1,'Group List(営業入力用)'!$A$1:$AT$925,3,0) -> 46220 | P8: 木 | Q8: 泊数 | S8: =L8-D8 -> 3 | U8: 仮予約期限 | W8: =VLOOKUP(A1,'Group List(営業入力用)'!$A$1:$AT$925,6,0) -> 46203 | AL8: =AF8*AH8*AJ8 -> 0 | AO8: ツイン
A9: 取引先 | D9: =VLOOKUP(A1,'Group List(営業入力用)'!$A$1:$AT$925,9,0) -> JNC | J9: 担当者 | L9: =VLOOKUP(A1,'Group List(営業入力用)'!$A$1:$AT$925,10,0) -> Seo Dongmi | P9: E-mail | R9: =VLOOKUP(A1,'Group List(営業入力用)'!$A$1:$AT$925,13,0) -> jnc.dongmi@gmail.com | AL9: =AF9*AH9*AJ9 -> 0 | AO9: エキストラBED
A10: 住所 | C10: =VLOOKUP(A1,'Group List(営業入力用)'!$A$1:$AT$925,11,0) -> 서울특별시 중구 태평로1가31-23건설회관 502호 | O10: 電話 | Q10: =VLOOKUP(A1,'Group List(営業入力用)'!$A$1:$AT$925,12,0) -> (82)02-722-7167 | T10: Fax | AL10: =AF10*AH10*AJ10 -> 0
A11: ★添乗員 | I11: TEL | K11: 08080227221 | P11: Email Fax | AL11: =AF11*AH11*AJ11 -> 0
AL12: =AF12*AH12*AJ12 -> 0
A13: Room Type | H13: Pax | I13: Rate | K13: =D8 -> 46217 | L13: 46218 | M13: 46219 | P13: =IF(P21=0,"",O13+1) | Q13: =IF(Q21=0,"",P13+1) | R13: =IF(R21=0,"",Q13+1) | S13: RmTTL | U13: Rate Total | AL13: =AF13*AH13*AJ13 -> 0
A14: Superior Twin | H14: 2 | I14: =(AF7-B$26-B$24)*H14 -> 14960 | K14: 4 | L14: 4 | M14: 4 | S14: =SUM(K14:R14) -> 12 | U14: =I14*S14 -> 179520 | AA14: 添乗員/乗務員 | AF14: 11000 | AH14: 1 | AJ14: 3 | AL14: =AF14*AH14*AJ14 -> 33000
I15: =(AF8-B$26-B$24)*H15 -> 0 | S15: =SUM(K15:R15) -> 0 | U15: =I15*S15 -> 0 | AA15: 小計 | AJ15: =SUM(AL7:AN14) -> 33000
I16: =(AF9-B$26-B$24)*H16 -> 0 | S16: =SUM(K16:R16) -> 0 | U16: =I16*S16 -> 0
A17: - | S17: =SUM(K17:R17) -> 0 | U17: =I17*S17 -> 0
A18: - | S18: =SUM(K18:R18) -> 0 | U18: =I16*S18 -> 0 | AA18: 消費税 | AJ18: =AJ15*0.1 -> 3300 | AO18: *10%にて計算
A19: - | S19: =SUM(K19:R19) -> 0 | U19: =I19*S19 -> 0 | AA19: 昼食 | AJ19: 1 | AL19: =AF19*AH19*AJ19 -> 0
A20: t/c, driver | H20: 1 | I20: =(AF14-B$26-B$24)*H20 -> 4800 | K20: 1 | L20: 1 | M20: 1 | S20: =SUM(K20:R20) -> 3 | U20: =I20*S20 -> 14400 | AA20: 入湯税 | AF20: 150 | AH20: =SUM(AH7:AI14) -> 1 | AJ20: 1 | AL20: =AF20*AH20*AJ20 -> 150
A21: Total | K21: =SUM(K14:K20) -> 5 | L21: =SUM(L14:L20) -> 5 | M21: =SUM(M14:M20) -> 5 | N21: =SUM(N14:N20) -> 0 | O21: =SUM(O14:O20) -> 0 | P21: =SUM(P14:P20) -> 0 | Q21: =SUM(Q14:Q20) -> 0 | R21: =SUM(R14:R20) -> 0 | S21: =SUM(K21:R21) -> 15 | U21: =SUM(U14:X20) -> 193920
A22: 食事 | AA22: 合計 | AH22: =SUM(AJ15,AJ18,AL19:AN21) -> 36450
A23: PKG料金（税別） | D23: １日目 | F23: 会場 | I23: 時刻 | K23: ２日目 | M23: 会場 | P23: 時刻 | R23: ３日目 | T23: 会場 | W23: 時刻
A24: 朝食 | B24: 2500 | D24: 朝食 | F24: あさ日・プレート | I24: 7:00～ | K24: 朝食 | P24: - | R24: 朝食 | W24: -
A25: 昼食 | D25: 昼食 | K25: 昼食 | P25: - | R25: 昼食 | W25: -
A26: 夕食 | B26: 3700 | D26: 夕食 | F26: ザ・プレート | K26: 夕食 | P26: - | R26: 夕食 | W26: -
A27: 宴会・メモ
A29: フロント チェック欄 | C29: <2日前> □館内案内作成 □名前シール作成 □部屋割り連絡 | T29: 担当 :
C30: □T/C案内 夕食(プレート00:00) 朝食(プレート) 六花(18:00) 到着時間(00:00) 人数() 到着棟() 案内方法() インター連絡() フロント電話番号()
C31: <1日前> □料金確認 □館内案内印刷 | T31: 担当 :
C32: <当日 > □名前シール印刷 □T/C到着時間確認 | T32: 担当 :
B33: その他 伝達事項

Sheet Group List(営業入力用)
A1: Group List | Q1: =SUBTOTAL(9,Q3:Q506) -> 28 | R1: =SUBTOTAL(9,R3:R506) -> 15 | S1: =SUBTOTAL(9,S3:S506) -> 1682 | T1: =SUBTOTAL(9,T3:T506) -> 1854
A2: Group No. | B2: C/I | C2: C/O | D2: Status | E2: 泊数 | F2: 仮予約期限 | G2: Group Name | H2: 概要 | I2: Agent / Corporate | J2: 先方担当者 | K2: 住所 | L2: 電話番号 | M2: E-mail | N2: Tour Type | O2: Nationalily | P2: Sales | Q2: T/C | R2: Dri | S2: Room TTL | T2: Guest pax | U2: ルームチャージ税別 | V2: Tour Number | W2: 【夜】ﾃﾅﾝﾄ | X2: 料金 | Y2: 【朝】ﾃﾅﾝﾄ | Z2: 料金 | AA2: 支払い方法 | AB2: バス到着時刻 | AC2: バス出発時刻 | AD2: 添乗員名 | AE2: 添乗員TEL | AF2: コミッション | AG2: Remarks（営業メモ用）
A3: 2026-049 | B3: 46216 | C3: 46217 | D3: 確定 | E3: 1 | G3: 株式会社 INPEX JAPAN 宮永勝 様 | H3: お客様を直江津燃料基地へご案内 | I3: 直受け | J3: 宮永勝 社長 | K3: 〒107-6332 東京都港区赤坂5-3-1 赤坂Bizタワー | L3: 03-3137-7539 | M3: masaru.miyanaga@inpex.co.jp | N3: MICE | O3: Japan | P3: 綿貫 | Q3: 1 | S3: 4 | T3: 4 | U3: 7000 | Y3: プレート | Z3: 2500 | AA3: 現払い | AB3: 0.74305556
A4: 2026-046 | B4: 46236 | C4: 46237 | D4: 仮予約 | E4: 1 | F4: 46174 | G4: 長岡花火大会 | H4: インバウンド募集 | I4: ㈱ジャパンホリデートラベル | J4: 王（Wang Wei） | K4: 〒163-1309 東京都新宿区西新宿6‐5‐1 新宿アイランドタワー9F | L4: 050-5490-1233 | N4: インバウンド | O4: 複数国 | P4: 畑村 | Q4: 1 | R4: 1 | S4: 20 | T4: 40 | U4: 27400 | W4: ― | Y4: Plate | Z4: 2200 | AA4: 売掛 | AB4: 1.0208333 | AF4: 10
A5: 2026-001 | B5: 45719 | C5: 45723 | D5: 確定 | E5: 3 | G5: 日本骨免疫学会 2026 学会 | H5: 学会開催 | I5: 直受け | J5: 森重様 | L5: 090-1947-9456 | M5: osteoimmunology.society@gmail.com | N5: MICE | O5: Japan | P5: Koike | S5: =(6+56+18)*3 -> 240 | T5: 80 | X5: 5280 | Z5: 3630 | AA5: 前払い | AF5: 0
A6: 2026-002 | B6: 46138 | C6: 46139 | D6: 仮 | E6: 1 | G6: 2026 ALOHA RNL TOUR #5 ハワイ在住日日系在住 | H6: 米国日系ハワイ来日団体 観光旅行 | I6: Air Apartment ご担当 後藤様 | J6: 後藤 | K6: 東京都新宿区西新宿8-11-10 星野ビル3階 | L6: 050-3488-5944 | M6: office@air-atokyo.com | O6: USA | P6: watanuki | Q6: 3 | R6: 1 | S6: 21 | T6: 44 | X6: 4224 | Z6: 2905 | AB6: 0.6875 | AC6: 0.39583333 | AD6: 3 | AE6: 2 | AF6: 0 | AG6: 手仕舞は１月末日 人数調整は７日前
A7: 2026-003 | B7: 45712 | C7: 45713 | D7: 仮予約 | E7: 1 | G7: GLOBIS ASリトリート（ GROUP①） | H7: MICE (募集型) | I7: グロービス | J7: 青木 | K7: 東京都千代田区二番町５番地１住友不動産麹町ビル | L7: 070-3762-2757 | M7: mie.aoki@globis.co.jp | N7: MICE | O7: Japan | P7: 横井
A8: 2026-004 | B8: 45713 | C8: 45714 | D8: 仮予約 | E8: 1 | G8: GLOBIS ASリトリート（ GROUP②） | H8: MICE (募集型) | I8: グロービス | J8: 青木 | K8: 東京都千代田区二番町５番地１住友不動産麹町ビル | L8: 070-3762-2757 | M8: mie.aoki@globis.co.jp | N8: MICE | O8: Japan | P8: 横井
A9: 2026-005 | B9: 45684 | C9: 45689 | D9: 仮予約 | E9: 5 | G9: Gendron Ski Tour | H9: 団体ツアー | I9: Gendron Ski | J9: Mélanie Dumont-Roussin | K9: 1465, boul. Mgr-Langlois, Salaberry-de-Valleyfield (QC) Canada, J6S 1C2 | L9: 450-373-8747 | M9: mdroussin@voyagesgendron.com | N9: ツアー | O9: Australia | P9: Koike | S9: 15 | T9: 28 | X9: 5280 | Z9: 3630 | AA9: 事前振込
A10: 2026-006 | B10: 45704 | C10: 45705 | D10: 仮予約 | E10: 1 | G10: GLOBIS ASリトリート（ GROUP①） | H10: MICE (募集型) | I10: グロービス | J10: 青木 | K10: 東京都千代田区二番町５番地１住友不動産麹町ビル | L10: 070-3762-2757 | M10: mie.aoki@globis.co.jp | N10: MICE | O10: Japan | P10: 横井
A11: 2026-007 | B11: 45705 | C11: 45706 | D11: 仮予約 | E11: 1 | G11: GLOBIS ASリトリート（ GROUP②） | H11: MICE (募集型) | I11: グロービス | J11: 青木 | K11: 東京都千代田区二番町５番地１住友不動産麹町ビル | L11: 070-3762-2757 | M11: mie.aoki@globis.co.jp | N11: MICE | O11: Japan | P11: 横井
A12: 2026-008 | B12: 46073 | C12: 46076 | D12: 仮予約 | E12: 3 | G12: 富洋海運 社員旅行 | H12: MICE | I12: 直受け | J12: 吉田様 | K12: 大阪府大阪市北区堂島２丁目３番８号 | L12: 080-3861-4517 | M12: y.yoshida@fuyokkk.co.jp | N12: MICE | O12: Japan | P12: Koike | S12: 73 | T12: 73 | X12: 5280 | Z12: 3630 | AA12: 事前カード決済 | AF12: 0 | AG12: 2025年からのリピーター
A13: 2026-009 | B13: 46084 | C13: 46088 | D13: 仮予約 | E13: 4 | G13: Natt様御一行 | H13: MICE | I13: Powder Ski Japan | J13: 上田様 | K13: P.O.Box 105155, Auckland City, 1143, New Zealand | L13: 09 281 2143 | M13: mail@powderskijapan.com | N13: MICE | O13: Thai | P13: Koike | S13: 80 | T13: 20 | X13: 5280 | Z13: 3630 | AA13: 事前振込
A14: 2026-010 | B14: 46034 | C14: 46039 | D14: 仮予約 | E14: 5 | G14: 260112孫先生ご一行 | H14: MICE | I14: KNT 仙台支店 | J14: ユー様 | K14: 宮城県仙台市青葉区中央4-6-1 SS30 15F | L14: 022-222-4141 | M14: t.yudan824@kntct.com | N14: MICE | O14: China | P14: Koike | S14: 13 | T14: 25 | X14: 5280 | Z14: 3630 | AA14: KNTクーポン
A15: 2026-011 | B15: 46033 | C15: 46037 | D15: 仮予約 | E15: 4 | G15: 台湾スキーツアー | H15: 募集ツアー | I15: 株式会社YKT | J15: チョウ様 | K15: 東京都江東区大島2-26-14 | L15: 03-5627-7878 | M15: info@ykt88.co.jp | N15: ツアー | O15: Taiwan | P15: Koike | S15: 18 | T15: 34 | X15: 5280 | Z15: 3630 | AA15: 事前振り込み
A16: 2026-012 | B16: 46061 | C16: 46065 | D16: 正式予約 | E16: 4 | G16: Japan Package FIT | H16: FIT | I16: Japan Package | J16: Daisuke Mizukoshi | K16: Add: PO BOX 3026, Asquith, NSW 2077 | M16: dai@japanpackage.com.au | N16: FIT | O16: Australia | P16: Koike | S16: 28 | T16: 21 | X16: 5280 | Z16: 3630 | AA16: 事前振り込み | AF16: 10
A17: 2026-013 | B17: 45685 | C17: 45689 | D17: 仮予約 | E17: 4 | G17: PAG Japan スキー旅行 | H17: 社員旅行 | I17: JTB BS第八事業部 | J17: 打矢様 | K17: 東京都千代田区霞が関3-2-5 霞が関ビルディング23階 | L17: 03-6737-9343 | M17: t_uchiya027@jtb.com | N17: MICE | O17: Japan | P17: Koike | S17: =21*4 -> 84 | T17: 21 | X17: 5280 | Z17: 3630 | AA17: JTBクーポン | AF17: 15
A18: 2026-014 | B18: 45668 | C18: 45672 | D18: 仮予約 | E18: 4 | G18: 0111 Powder Holidays FIT | H18: FIT | I18: Powder Holidays | J18: Ms. Mayumi Terakado | K18: 13/50 Cavill Ave Surfers Paradise QLD 4217 | L18: 1300 527 267 | M18: mayumi@powderholidays.com | N18: FIT | O18: Japan | P18: Koike | S18: 8 | T18: 4 | X18: 5280 | Z18: 3630 | AA18: 事前振り込み | AF18: 10
A19: 2026-015 | B19: 46038 | C19: 46039 | D19: 仮予約 | E19: 1 | G19: 妙高ツーリズムマネージメント | H19: 募集ツアー | I19: インバンド宿泊 | J19: 蔡紋如 | K19: 新潟県妙高市大字田口309番地1 | L19: 0255-86-2412 | M19: myokotaiwan@gmail.com | N19: ツアー | O19: 台湾 | P19: 横井 | S19: 20 | T19: 10 | AD19: 2
A20: 2026-016 | B20: 46059 | C20: 46060 | D20: 仮予約 | E20: 1 | G20: 妙高ツーリズムマネージメント | H20: 募集ツアー | I20: インバンド宿泊 | J20: 蔡紋如 | K20: 新潟県妙高市大字田口309番地2 | L20: 0255-86-2413 | M20: myokotaiwan@gmail.com | N20: ツアー | O20: 台湾 | P20: 横井 | S20: 20 | T20: 10 | AD20: 2
A21: 2026-017 | B21: 46036 | C21: 46042 | D21: 仮予約 | E21: 6 | G21: Ski Japan Holidays FIT | H21: FIT | I21: Ski Japan Holidays | J21: 稲永様 | K21: 6660 Hokujo Hakuba-mura Kitaazumi-gun Nagano-ken Japan 〒399-9301 | L21: 81 (0)261 72 6663 | M21: bookings@japanspecialists.com | N21: FIT | O21: Australia | P21: Koike | S21: 2 | T21: 4 | X21: 5280 | Z21: 3630 | AA21: 事前振り込み | AF21: 10
A22: 2026-018 | B22: 46060 | C22: 46067 | D22: 確定 | E22: 7 | G22: Mogul Ski FIT | H22: FIT | I22: Mogul Ski | J22: Edgar Beck | K22: Level 1, 464 High Street, Prahran, VIC, 3181 Australia | L22: +61 395 252 555 | M22: edgar@mogulski.com.au | N22: FIT | O22: Australia | P22: Koike | S22: 2 | T22: 7 | X22: 5280 | Z22: 3630 | AA22: 事前振り込み | AF22: 10
A23: 2026-019 | B23: 46055 | C23: 46061 | D23: 仮予約 | E23: 6 | G23: 中国スキー団体（ハルビン国際旅行社） | H23: 募集ツアー | I23: ハルビン国際旅行社 | J23: 近藤 みき | L23: 025-383-6211 | M23: aha261720@gmail.com | N23: ツアー | O23: China | P23: Koike | S23: 60 | T23: 21 | X23: 5280 | Z23: 3630 | AA23: 事前振り込み | AD23: 1 | AF23: 10
A24: 2026-020 | B24: 46038 | C24: 46044 | D24: 仮予約 | E24: 6 | G24: Mogul Ski FIT | H24: FIT | I24: Mogul Ski | J24: Jason Grondman | K24: Level 1, 464 High Street, Prahran, VIC, 3181 Australia | L24: +61 395 252 555 | M24: jason@mogulski.com.au | N24: FIT | O24: Australia | P24: Koike | S24: 12 | T24: 5 | X24: 5280 | Z24: 3630 | AA24: 事前振り込み | AF24: 10
A25: 2026-021 | B25: 46057 | C25: 46059 | D25: 確定 | E25: 2 | G25: Different Snow FIT | H25: FIT | I25: Different Snow | J25: Nick Coates | L25: +44(0)1242 242 505 | M25: nick@differentsnow.com | N25: FIT | O25: Australia | P25: Koike | S25: 8 | T25: 4 | X25: 5280 | Z25: 3630 | AA25: 事前振り込み | AF25: 10
A26: 2026-022 | B26: 45827 | C26: 45829 | D26: 確定 | E26: 2 | G26: 北信越高等学校バレーボール大会 | H26: 教育旅行 | I26: 日本旅行 新潟支店 | J26: 加藤 美花 | L26: 025-248-6161 | M26: mika_kato@nta.co.jp | N26: 教育旅行 | O26: Japan | P26: Koike | S26: 24 | T26: 40 | X26: 3900 | Z26: 2200 | AA26: クーポン | AF26: 10
A27: 2026-023 | B27: 46135 | C27: 45771 | D27: 確定 | E27: 1 | G27: ER-260420 東北ジャパンネットワーク ツアー | I27: 東北ジャパンネットワーク | J27: 許 | L27: 050-6864-6228 | M27: kyo@tohokujapan.net | N27: 募集ツアー | O27: Taiwan | P27: Koike | S27: 13 | T27: 24 | X27: 3700 | Z27: 2500 | AA27: 事前振り込み | AF27: 10
A28: 2026-024 | B28: 45688 | C28: 45692 | D28: 仮予約 | E28: 4 | G28: Japan Dimention Ski tour (USA) | H28: MICE | I28: Japan Dimention | J28: 木村 | K28: 三重県四日市市小杉町605 | L28: 070-4332-6734 | M28: partners@japan-dimension.com | N28: MICE | O28: USA | P28: Koike | S28: 9 | T28: 9 | X28: 5280 | Z28: 3630 | AA28: 事前振り込み | AF28: 10
A29: 2026-025 | B29: 46025 | C29: 46030 | D29: 仮予約 | E29: 5 | G29: 0103 KODO Travel FIT | H29: FIT | I29: KODO Travel | J29: 玉川 美沙 | K29: 群馬県利根郡みなかみ町湯檜曽45 | L29: 080-4923-1477 | M29: misa@kodotravel.com | N29: MICE | P29: Koike | S29: 1 | T29: 2 | X29: 5280 | Z29: 3630 | AA29: 事前振り込み | AF29: 10
A30: 2026-026 | B30: 45659 | C30: 45662 | D30: 仮予約 | E30: 3 | G30: wondertrunk&co. FIT | I30: wondertrunk&co. | J30: 帆足 様 | K30: 〒150-0042 東京都渋谷区宇田川町3-7 ヒューリック渋谷公園通りビル3F | L30: 03-6427-8402 | M30: ema@wondertrunk.co | N30: FIT | O30: USA | P30: Koike | S30: 1 | T30: 2 | X30: 5280 | Z30: 3630 | AA30: 事前振り込み | AF30: 10
A31: 2026-027 | B31: 45683 | C31: 45686 | D31: 確定 | E31: 3 | F31: 45940 | G31: 0126 Japan Holidays FIT | H31: FIT | I31: Japan Holidays | J31: 横川 様 | K31: 長野県北安曇郡白馬村6660 | L31: 0261-72-6663 | M31: bookings@japanspecialists.com | N31: FIT | O31: Australia | P31: Koike | S31: 3 | T31: 2 | X31: 5280 | Z31: 3630 | AA31: 事前振り込み | AF31: 10
A32: 2026-028 | B32: 45688 | C32: 45689 | D32: 仮予約 | E32: 1 | G32: エーオングループジャパン株式会社 | H32: 社員旅行 | I32: 直受け | J32: 鷲尾 直樹 | K32: 東京都千代田区永田町2-10-3キャピトルタワー11階 | L32: 03-4589-4270 | M32: naoki.washio@aon.com | O32: Japan | P32: yokoi | S32: 30 | T32: 10 | X32: 5280 | Z32: 3630 | AF32: 0
A33: 2026-029 | B33: 45658 | C33: 45659 | D33: 確定 | E33: 1 | G33: 雪の森株式会社 FIT | H33: FIT | I33: 雪の森株式会社 | J33: 平馬 新 | K33: 〒949-6212 新潟県南魚沼郡湯沢町三国348-3 | L33: 070-8976-7878 | M33: heima@yukinomori.com | N33: FIT | O33: Taiwan | P33: Koike | S33: 1 | T33: 3 | Z33: 3630 | AA33: 現地払い | AF33: 0
A34: 2026-030 | B34: 45673 | C34: 45674 | D34: 仮予約 | E34: 2 | F34: 46007 | G34: イギリスメディア FAMツアー | H34: メディアツアー | I34: 淡雪合同会社 | J34: ジェニファー スピッツ | K34: 〒951-8067 新潟県新潟市中央区本町通12番町2782番地 | L34: 080-3254-4769 | M34: Jen@awayuki.com | N34: FIT | O34: England | P34: Koike | S34: 8 | T34: 9 | Z34: 3630 | AA34: 全旅クーポン | AF34: 0
A35: 2026-031 | B35: 46303 | C35: 46304 | D35: 第１候補 他は10/6 10/7が候補 | E35: 1 | F35: ※2025年12月中旬には日程日が確定します | G35: ５県 議会事務局会議 会議/懇親会 | H35: 北陸５県 議会事務局 事務局長会議 | I35: 妙高市役所 議会事務局 | J35: 横田こうえつ様 | K35: 妙高市役所 議会事務局様が2026年度持ち回り県担当 | L35: 0255-74-0043 | N35: 参加募集 | O35: Japan | P35: 綿貫 | S35: 60 | T35: 60 | Z35: 2500 | AA35: 後日請求 | AG35: 2025年11月21日現在に於いて連絡あり、10/6-7 7-8 8-9 ８日の確定が濃厚
A36: 2026-032 | B36: 46147 | C36: 46150 | D36: 仮予約 | E36: 3 | F36: 46017 | G36: 学校法人東京インターナショナルスクール | H36: 修学旅行 | I36: JTB教育第一事業部 | J36: 米谷 真鈴 | K36: 〒141-0021 東京都目黒区上大崎2-24-9 目黒IKビル3階 | L36: 03-6631-3219 | M36: m_kometani068@jtb.com | N36: 教育旅行 | O36: foreign | P36: Koike | S36: 22 | T36: 51 | X36: 3600 | Z36: 1870 | AA36: JTBクーポン | AF36: 15
A37: 2026-033 | B37: 46275 | C37: 46276 | D37: 仮予約 | E37: 1 | F37: 46017 | G37: 新潟県立新潟よつば学園 小学部 | H37: 修学旅行 | I37: 東武トップツアーズ 新潟市絵th | J37: 川野 青葉 | K37: 〒950-0912 新潟県新潟市中央区南笹口1-1-54 日生南笹口ビル5階 | L37: 050-9001-8753 | M37: aoba_kawano@tobutoptours.co.jp | N37: 教育旅行 | O37: Japan | P37: Koike | S37: 5 | T37: 9 | X37: 3900 | Z37: 2200 | AF37: 10
A38: 2026-034 | B38: 46087 | C38: 46089 | D38: 確定 | E38: 3 | G38: インバウンド宿泊 | H38: スノーボード旅行 | I38: 直受け | J38: 柿栖 | L38: 070-6489－4095 | M38: kakisu <kakisu@matisse-consul.co.jp> | P38: 横井 | X38: 5280 | Z38: 3630
A39: 2026-035 | B39: 46087 | C39: 46090 | D39: 確定 | E39: 4 | G39: インバウンド宿泊 | H39: スノーボード旅行 | I39: 直受け | J39: 柿栖 | L39: 070-6489－4096 | M39: kakisu <kakisu@matisse-consul.co.jp> | P39: 横井 | X39: 5280 | Z39: 3630
A40: 2026-036 | B40: 46274 | C40: 46275 | D40: 確定 | E40: 1 | G40: 全国春日連合会 | H40: 年次総会 | I40: 頸城観光 | J40: 佐藤三郎 | K40: 〒942-0004 新潟県上越市西本町2-3-21 | L40: 025-543-4133 | M40: sato@kubikikanko.com | N40: MICE | O40: Japan | P40: Koike | Q40: 1 | S40: 53 | T40: 53 | X40: 8000 | Z40: 3080 | AA40: 一部前払い | AF40: 10 | AG40: 全国の春日神社の連合、本部は奈良
A41: 2026-037 | B41: 46195 | C41: 46197 | D41: 仮予約 | E41: 2 | F41: 46031 | G41: サレジアン国際学園様 中等部 | H41: オリエンテーション | I41: 妙高ツーリズムマネジメント | J41: 舘野 智光 | L41: 025-582-3935 | M41: tateno@myoko-gt.com | N41: 教育旅行 | O41: Japan | P41: Koike | S41: 70 | T41: 140 | X41: 3900 | Z41: 2200 | AA41: 後請求 | AF41: 10 | AG41: 昼食あり @1500円
A42: 2026-038 | B42: 46197 | C42: 46199 | D42: 仮予約 | E42: 2 | F42: 46031 | G42: サレジアン国際学園様 高等部 | H42: オリエンテーション | I42: 妙高ツーリズムマネジメント | J42: 舘野 智光 | L42: 025-582-3935 | M42: tateno@myoko-gt.com | N42: 教育旅行 | O42: Japan | P42: Koike | S42: 140 | T42: 235 | X42: 3900 | Z42: 2200 | AA42: 後請求 | AF42: 10 | AG42: 昼食あり @1500円
A43: 2026-039 | B43: 46106 | C43: 46109 | D43: 仮予約 | E43: 3 | G43: 国際高等学校 中等部 | H43: スキーキャンプ | I43: 直接予約 | J43: 角 梓 | K43: 4-4 Sagamine, Komenoki, Nisshin, Aichi, Japan, 470-0193, | L43: 056-173-8181 | M43: azusa_sumi@ic.nucba.ac.jp | N43: 教育旅行 | O43: foreign | P43: koike | S43: 23 | T43: 55 | X43: 5280 | Z43: 3630 | AA43: 後請求
A44: 2026-040 | B44: 45943 | C44: 45945 | D44: 仮予約 | E44: 2 | F44: 46055 | G44: 2026 Bicycle Adventures / Cycling trip to Shinshu-Hokuriku | H44: 募集ツアー | I44: 株式会社近畿日本ツーリスト グローバル営業支店 | K44: 東京都千代田区神田和泉町1-13 住友商事神田和泉町ビル14F | L44: 03-6891-9200 | M44: k.yokoyama692@kntct.com | N44: MICE | O44: USA | P44: Koike | S44: 12 | T44: 1 | X44: 5280 | Z44: 3630 | AA44: クーポン | AF44: 15
A45: 2026-041 | B45: 46156 | C45: 46157 | D45: 仮予約 | E45: 1 | F45: 46094 | G45: PCG ペイシャンスキャピトルグループ 役員・社員様近隣エリア視察 | H45: 参加案内に於いて人数確定 ※現段階では他ホテル相見積 | I45: 直受け | J45: 川崎恵理 様 | K45: 〒100-0005 東京都千代田区丸の内2-1-1 明治安田生命ビル5F | L45: 080-3019-6209 | M45: eri@pcg.ltd | N45: 団体 | O45: Japan | P45: 綿貫 | S45: 60 | T45: 60 | Z45: 3630 | AG45: 杉野沢エリア 上越近隣エリア視察
A46: 2026-042 | B46: 46116 | C46: 46117 | D46: 仮予約 | E46: 1 | G46: 新進新潟0401JP | H46: 台湾募集ツアー | I46: 新進旅行社 | J46: JACK / 陳煒佳 / 姚 | K46: 台湾北市中山區松江路 76 号 2階 | L46: 886-2-2561-7788 | N46: 団体 | O46: 台湾 | P46: 畑村 | Q46: 1 | R46: 1 | S46: 12 | T46: 24 | X46: 3300 | Y46: プレート | Z46: 2200 | AA46: 前受
A47: 2026-043 | B47: 46136 | C47: 46137 | D47: 仮予約 | E47: 1 | G47: 妙高ツーリズムマネージメント インバウンド 宿泊 | H47: 台湾募集ツアー | I47: 旅行 | J47: 蔡紋如 | K47: 新潟県妙高市大字田口309番地1 | L47: 0255-86-2412 | M47: myokotaiwan@gmail.com | N47: 団体 | O47: 台湾 | P47: 横井 | Q47: 1 | R47: 1 | S47: 20 | T47: 10
A48: 2026-044 | B48: 46137 | C48: 46138 | D48: 仮予約 | E48: 1 | G48: 妙高ツーリズムマネージメント インバウンド 宿泊 | H48: 台湾募集ツアー | I48: 旅行 | J48: 蔡紋如 | K48: 新潟県妙高市大字田口309番地1 | L48: 0255-86-2412 | M48: myokotaiwan@gmail.com | N48: 団体 | O48: 台湾 | P48: 横井 | Q48: 1 | R48: 1 | S48: 20 | T48: 10
A49: 2026-045 | B49: 46165 | C49: 46166 | D49: 確定 | E49: 1 | G49: Audi TT Meeting 2026 | H49: 事務局/幹事は当方手配 ※一般参加者はAudi ホームページからプロモーションコードに応募⇔宿泊とする | I49: 直 | J49: 福嶋鉄平 | K49: 〒381-2213 長野市広田3 | L49: 026-284-5102 | M49: info@runaway.co.jp | N49: car event | O49: japan | P49: 綿貫 | S49: 23 | T49: 32
A50: 2026-047 | B50: 46140 | C50: 46143 | D50: 仮予約 | E50: 4 | F50: 46112 | G50: ハウメット・シズテムズ・ジャパン 様 | H50: 5/1 仮予定 インセンティブパーティー開催 ※海外の方 | I50: 直受け | J50: 水谷しずる様 | K50: 〒942-0032 新潟県上越市福田1 上越テクノセンター | L50: 080-7847-4601 | M50: chizuru.mizutani@howmet.com | N50: 日帰りパーティー | O50: Japan | P50: 綿貫 | S50: 16 | T50: 16 | Z50: 3630 | AA50: 現払い
A51: 2026-048 | B51: 46235 | C51: 46236 | E51: 1 | F51: 46053 | G51: 上越産業株式会社60周年祝賀会 | H51: 創業1966年、創業60周年の周年行事 | I51: ㈱日本旅行 長岡支店 | J51: 長岡 佳則 | K51: 〒940-0071 新潟県長岡市表町1-11-1 長岡フロントビル6階 | L51: 0258-88-2500 | M51: yoshinori_nagaoka@nta.co.jp | N51: 団体 | T51: 40 | W51: はねうま | X51: 8000 | Y51: プレート | Z51: 3630 | AA51: 後請求
A52: 2026-050 | B52: 46129 | C52: 46130 | D52: 確定 | E52: 1 | G52: 84485ホテル立山とアルペンルート | H52: エスコート | I52: クラブツーリズム | J52: 山西 | K52: 〒107-6332 東京都港区赤坂5-3-2 赤坂Bizタワー | L52: ０７０‐2649₋9956 | N52: エスコート | O52: Japan | P52: 畑村 | Q52: 1 | R52: 1 | S52: 14 | T52: 28 | U52: 13000 | W52: Plate | X52: 3300 | Y52: Plate | Z52: 2200
A53: 2026-051 | B53: 46132 | C53: 46133 | D53: 確定 | E53: 1 | G53: 84486ホテル立山とアルペンルート | H53: エスコート | I53: クラブツーリズム | J53: 山西 | K53: 〒107-6332 東京都港区赤坂5-3-2 赤坂Bizタワー | L53: ０７０‐2649₋9956 | N53: エスコート | O53: Japan | P53: 畑村 | Q53: 1 | R53: 1 | S53: 14 | T53: 28 | U53: 13000 | W53: Plate | X53: 3300 | Y53: Plate | Z53: 2200
A54: 2026-052 | B54: 46135 | C54: 46136 | D54: 確定 | E54: 1 | G54: 84487ホテル立山とアルペンルート | H54: エスコート | I54: クラブツーリズム | J54: 山西 | K54: 〒107-6332 東京都港区赤坂5-3-2 赤坂Bizタワー | L54: ０７０‐2649₋9956 | N54: エスコート | O54: Japan | P54: 畑村 | Q54: 1 | R54: 1 | S54: 14 | T54: 28 | U54: 13000 | W54: Plate | X54: 3300 | Y54: Plate | Z54: 2200
A55: 2026-053 | B55: 46125 | C55: 46126 | D55: 確定 | E55: 1 | G55: ４T05 春の高山祭・高田の夜桜・高遠③ | H55: エスコート | I55: 阪急交通社 松山支店 | J55: 辻田 | K55: 〒880－0806 宮崎市広島１－18－12 宮崎フコク生命ビル３F | L55: 0985－26－2626 | N55: エスコート | O55: Japan | P55: 畑村 | Q55: 1 | R55: 1 | S55: 17 | T55: 31 | U55: 17400 | W55: Plate | X55: 3300 | Y55: Plate | Z55: 2200
A56: 2026-054 | B56: 46137 | C56: 46138 | D56: 確定 | E56: 1 | G56: 家族旅行（アワシマ様） | I56: 新富旅行株式会社 | J56: 竹鼻 | K56: 〒930-0041富山県富山市向川原町2ｰ23ダイアパレス雪見橋１F | L56: 076ｰ491-3223 | M56: str-kk@nzm.jrnet.ne.jp | N56: 個人 | O56: Japan | P56: 横井 | Q56: 1 | R56: 1 | S56: 7 | T56: 14 | W56: Plate | X56: 5280 | Y56: Plate | Z56: 3630 | AG56: 添寝 お食事費用 5,170円（税別）
A57: 2026-055 | B57: 46328 | C57: 46329 | D57: 仮予約 | E57: 1 | F57: 46203 | G57: LON-1031 | H57: 台湾ツアー | I57: LION TRAVEL | J57: 黃冠穎 | K57: 台北市內湖區石潭路151號 | L57: +886-922-966-308 | M57: karinahuang@liontravel.com | N57: ツアー | O57: Japan | P57: 小池 | Q57: 2 | R57: 1 | S57: 15 | T57: 33 | W57: Plate | X57: 4000 | Y57: Plate | Z57: 2800 | AA57: 現地一括
A58: 2026-056 | B58: 46335 | C58: 46336 | D58: 仮予約 | E58: 1 | F58: 46203 | G58: LION-1107 | H58: 台湾ツアー | I58: LION TRAVEL | J58: 黃冠穎 | K58: 台北市內湖區石潭路151號 | L58: +886-922-966-308 | M58: karinahuang@liontravel.com | N58: ツアー | O58: Japan | P58: 小池 | Q58: 2 | R58: 1 | S58: 15 | T58: 33 | W58: Plate | X58: 4000 | Y58: Plate | Z58: 2800 | AA58: 現地一括
A59: 2026-057 | B59: 46210 | C59: 46212 | D59: 確定 | E59: 3 | G59: ファスティングライフ株式会社 | H59: 視察研修 | I59: 直受け | J59: 阿部泰三 | K59: 〒130-0022 東京都墨田区江東橋2-3-11 ベルナ錦糸町１階 | L59: 03-6659-9571 | N59: 団体 | O59: Japan | P59: 綿貫 | S59: 50 | T59: 70 | W59: あさ日 | X59: 5280 | Y59: Plate | Z59: 3630 | AA59: 現地一括
A60: 2026-058 | B60: 46222 | C60: 46223 | D60: 確定 | E60: 1 | G60: ピーナッツ会 | H60: MICE | I60: トラベル愛ランド | J60: 水口 亜由美 | K60: 石川県七尾市御祓町1番地 パトリア1階 | L60: 0767-53-7744 | M60: ayumi@travelailand.com | N60: 団体 | O60: Japan | P60: 小池 | R60: 1 | S60: 11 | T60: 13 | X60: 4000 | Z60: 2800 | AA60: JTBクーポン | AF60: 15
A61: 2026-059 | B61: 46097 | C61: 46099 | D61: 確定 | E61: 2 | G61: デヴィご夫人 他 ご一行様 | H61: 一般 | I61: 直受け | J61: 田中見佳 様 | K61: オフィス スカルノ事務所 〒東京都渋谷区神山町31-1 | L61: 03-5465-0050 | N61: 個人 | O61: Japan | P61: 綿貫 | S61: 2 | T61: 4 | U61: 40000 | Z61: 3630 | AA61: 現地一括 | AG61: クラブ＃2502 デヴィ夫人田中見佳様 ＃2504都築多佳恵様 新出
A62: 2026-060 | B62: 46116 | C62: 46117 | D62: 確定 | E62: 1 | G62: 3059M 「高田の桜」と「高遠の桜」信越名城と善光寺・富士 3日間 | H62: エスコート | I62: ㈱阪急交通社 宮崎支店 | J62: 松崎 夏美 | K62: 880-0806 宮崎市広島1-18-12 宮崎フコク生命ビル3階 | L62: 0985‐26‐3636 | N62: ツアー | O62: Japan | P62: 畑村 | Q62: 1 | R62: 1 | S62: 12 | T62: 24 | V62: ３０５９M | W62: Plate | X62: 3300 | Y62: Plate | Z62: 2200
A63: 2026-061 | B63: 46273 | C63: 46276 | D63: 確定 | E63: 3 | G63: ファスティングライフ株式会社 | H63: 視察研修 | I63: 直受け | J63: 阿部泰三様 | K63: 〒130-0022 東京都墨田区江東橋2-3-11 ベルナ錦糸町１階 | L63: 03-6659-9571 | N63: 団体 | O63: Japan | P63: 綿貫 | S63: 50 | T63: 70 | W63: あさ日 | X63: 5280 | Y63: Plate | Z63: 3630 | AA63: 現地一括
A64: 2026-062 | B64: 46103 | C64: 46106 | D64: 確定 | E64: =C64-B64 -> 3 | G64: 第53回 全国高等学校選抜卓球大会 | H64: 教育旅行 | I64: 日本旅行 新潟支店 | J64: 加藤 美花 | L64: 025-248-6161 | M64: mika_kato@nta.co.jp | N64: 団体 | O64: Japan | P64: 小池 | X64: 3900 | Z64: 2200 | AF64: 15
A65: 2026-063 | B65: 46165 | C65: 46165 | D65: 仮予約 | F65: 46097 | G65: 日帰り会議/懇親会 JCI妙高青年会議所 | H65: MICE | I65: 直受け | J65: 小島奨吾様 | K65: 勤務地〒950-0087 新潟市中央区東大通2-4-4 日生不動産ビル6F | L65: 090-4545-8105 | M65: syhyk0827@yahoo.co.jp | N65: 団体 | O65: Japan | P65: 綿貫 | AG65: セミナールーム会議80名 はねうま会場 懇親会 料理￥6.000/税別 飲み放題￥3.500/別 ※会場費用￥50.000/税別 他所のホテルと競合 相見積もり中
A66: 2026-064 | B66: 46174 | C66: 46175 | D66: 仮予約 | E66: 1 | F66: 46127 | G66: 旧三和中卒業生同窓会 | H66: 同窓会直受け | I66: 直受け | J66: 金子恵美様 | K66: 勤務先 妙高市朝日町１丁目８-1 | L66: 0120-72-2516 | N66: 団体 | O66: Japan | P66: 綿貫 | S66: 10 | T66: 20 | W66: あさ日 | X66: 6000 | Y66: Plate | Z66: 3630 | AG66: 4/15日までに確認 ※返信締切日確認
A67: 2026-065 | B67: 46185 | C67: 46186 | D67: 仮予約 | E67: 1 | F67: 確定 | G67: 妙高グリーンエナジー株式会社 | H67: 懇親会 宿泊 | I67: 直受け | J67: 渡辺将和 様 | K67: 〒944-0005 妙高市中川3番20号 | L67: 0255-72-3566 | N67: 団体 | O67: Japan | P67: 綿貫 | S67: 4 | T67: 8 | W67: あさ日 | X67: 5800 | Y67: Plate | Z67: 3630 | AG67: ※昨年度に引き続き2回目 確定済み
A68: 2026-066 | B68: 46136 | C68: 46137 | D68: 確定 | E68: 1 | F68: 確定 | G68: 2026 ALOHA RNL TOUR #5 ハワイ在住日日系在住 | H68: 米国日系ハワイ来日団体 観光旅行 | I68: Air Apartment ご担当 後藤様 | J68: 後藤 | K68: 東京都新宿区西新宿8-11-10 星野ビル3階 | L68: 050-3488-5944 | M68: office@air-atokyo.com | O68: USA | P68: watanuki | Q68: 3 | R68: 1 | S68: 25 | T68: 41 | X68: 4224 | Z68: 2905 | AB68: 0.6875 | AC68: 0.39583333 | AD68: 3 | AE68: 2 | AF68: 0 | AG68: 3.6現在人数減の連絡に於いて催行がある旨発覚する 人数調整は７日前
A69: 2026-067 | B69: 46167 | C69: 46168 | D69: 確定 | E69: 1 | F69: 確定 | G69: 妙高グリーンエナジー株式会社 | H69: 懇親会 宿泊 | I69: 直受け | J69: 渡辺将和 様 | K69: 〒944-0005 妙高市中川3番20号 | L69: 0255-72-3566 | N69: 団体 | O69: Japan | P69: 綿貫 | S69: 2 | T69: 2 | X69: 5280 | Z69: 3630 | AG69: 北陸ガス社長 敦井様 古俣常務様 ２名の宿泊 ※グリーンエナジー様9名日帰
A70: 2026-068 | B70: 46196 | C70: 46199 | D70: 確定 | E70: 3 | F70: 確定 | G70: JNC 韓国インバウンドツアー | H70: インバウンドツアー | I70: JNC | J70: Seo Dongmi | K70: 서울특별시 중구 태평로1가31-23건설회관 502호 | L70: (82)02-722-7167 | M70: jnc.dongmi@gmail.com | N70: ツアー | O70: Korea | P70: 小池 | Q70: 1 | S70: 6 | T70: 10 | W70: Plate | X70: 4000 | Y70: Plate | Z70: 2800 | AF70: 10
A71: 2026-069 | B71: 46263 | C71: 46264 | D71: 仮予約 | E71: 1 | F71: 確認中 | G71: 会議を含む宿泊イベントを企画 | H71: オフサイドミーティング | I71: 直受け | J71: 奥垣 安 | K71: 〒940-0066 新潟県長岡市東坂之上町3-2-6 日本生命長岡ビル2Ｆ | L71: 080-5098-2808 | M71: okugaki59078@nissay.co.jp | N71: 団体 | O71: Japan | P71: 横井
A72: 2026-070 | B72: 46217 | C72: 46220 | D72: 仮予約 | E72: 3 | F72: 46203 | G72: JNC 韓国インバウンドツアー | H72: インバウンドツアー | I72: JNC | J72: Seo Dongmi | K72: 서울특별시 중구 태평로1가31-23건설회관 502호 | L72: (82)02-722-7167 | M72: jnc.dongmi@gmail.com | N72: ツアー | O72: Korea | P72: 小池 | Q72: 1 | S72: 12 | T72: 9 | W72: Plate | X72: 4000 | Y72: Plate | Z72: 2800 | AF72: 10
A73: 2026-071 | B73: 46231 | C73: 46234 | D73: 仮予約 | E73: 3 | F73: 46201 | G73: JNC 韓国インバウンドツアー | H73: インバウンドツアー | I73: JNC | J73: Seo Dongmi | K73: 서울특별시 중구 태평로1가31-23건설회관 502호 | L73: (82)02-722-7167 | M73: jnc.dongmi@gmail.com | N73: ツアー | O73: Korea | P73: 小池 | Q73: 1 | S73: 12 | T73: 9 | W73: Plate | X73: 4000 | Y73: Plate | Z73: 2800 | AF73: 10
A74: 2026-072 | B74: 46238 | C74: 46241 | D74: 仮予約 | E74: 3 | F74: 46207 | G74: JNC 韓国インバウンドツアー | H74: インバウンドツアー | I74: JNC | J74: Seo Dongmi | K74: 서울특별시 중구 태평로1가31-23건설회관 502호 | L74: (82)02-722-7167 | M74: jnc.dongmi@gmail.com | N74: ツアー | O74: Korea | P74: 小池 | Q74: 1 | S74: 12 | T74: 9 | W74: Plate | X74: 4000 | Y74: Plate | Z74: 2800 | AF74: 10
A75: 2026-073 | B75: 46252 | C75: 46255 | D75: 仮予約 | E75: 3 | F75: 46221 | G75: JNC 韓国インバウンドツアー | H75: インバウンドツアー | I75: JNC | J75: Seo Dongmi | K75: 서울특별시 중구 태평로1가31-23건설회관 502호 | L75: (82)02-722-7167 | M75: jnc.dongmi@gmail.com | N75: ツアー | O75: Korea | P75: 小池 | Q75: 1 | S75: 12 | T75: 9 | W75: Plate | X75: 4000 | Y75: Plate | Z75: 2800 | AF75: 10
A76: 2026-074 | B76: 46259 | C76: 46262 | D76: 仮予約 | E76: 3 | F76: 46228 | G76: JNC 韓国インバウンドツアー | H76: インバウンドツアー | I76: JNC | J76: Seo Dongmi | K76: 서울특별시 중구 태평로1가31-23건설회관 502호 | L76: (82)02-722-7167 | M76: jnc.dongmi@gmail.com | N76: ツアー | O76: Korea | P76: 小池 | Q76: 1 | S76: 12 | T76: 9 | W76: Plate | X76: 4000 | Y76: Plate | Z76: 2800 | AF76: 10
A77: 2026-075
A78: 2026-076
A79: 2026-077
A80: 2026-078
A81: 2026-079
A82: 2026-080
A83: 2026-081
A84: 2026-082
A85: 2026-083
A86: 2026-084
A87: 2026-085
A88: 2026-086
... A250: 2026-248
A251: 2026-249 | E251: =C251-B251 -> 0
A252: 2026-250 | E252: =C252-B252 -> 0
A253: 2026-251 | E253: =C253-B253 -> 0
A254: 2026-252 | E254: =C254-B254 -> 0
A255: 2026-253 | E255: =C255-B255 -> 0
A256: 2026-254 | E256: =C256-B256 -> 0
A257: 2026-255 | E257: =C257-B257 -> 0
A258: 2026-256 | E258: =C258-B258 -> 0
A259: 2026-257 | E259: =C259-B259 -> 0
A260: 2026-258 | E260: =C260-B260 -> 0
A261: 2026-259 | E261: =C261-B261 -> 0
...
